Workbook

Sheet Overview
B3: DYNAMIC HOME SOLUTIONS (DHS) | PORTFOLIO OVERVIEW | J3: AS OF SEPTEMBER 24, 2026
B4: 42 North — Retail Flooring Proposals
B5: 20 customer-facing proposals across 42 North locations — live totals linked to each proposal tab
B8: TOTAL PROPOSAL VALUE | D8: COMPLETED | F8: IN PROCESS | I8: OPEN PROPOSALS
B9: =SUM($K$14:$K$33) | D9: =SUMIF($D$14:$D$33,"Completed",$K$14:$K$33) | F9: =SUMIF($D$14:$D$33,"In process",$K$14:$K$33) | I9: =SUMIF($D$14:$D$33,"Proposal",$K$14:$K$33)+SUMIF($D$14:$D$33,"Needs revisit",$K$14:$K$33)
B10: 20 proposals | D10: =COUNTIF($D$14:$D$33,"Completed")&" proposals" | F10: =COUNTIF($D$14:$D$33,"In process")&" proposals" | I10: =(COUNTIF($D$14:$D$33,"Proposal")+COUNTIF($D$14:$D$33,"Needs revisit"))&" proposals (incl. needs-revisit)"
B13: # | C13: PROPOSAL | D13: STATUS | E13: SCOPE | F13: TAX RATE | G13: LABOR | H13: MATERIALS | I13: FREIGHT | J13: TAX | K13: TOTAL | L13: DEPOSIT (50%)
B14: 1 | C14: Gentle Dental Braintree | D14: Completed | E14: LVT & carpet tile flooring | F14: 6.25% | G14: ='Completed - GD Braintree'!F34 | H14: ='Completed - GD Braintree'!F35 | I14: ='Completed - GD Braintree'!F36 | J14: ='Completed - GD Braintree'!F37 | K14: ='Completed - GD Braintree'!F38 | L14: ='Completed - GD Braintree'!F39
B15: 2 | C15: Abington Family Dental | D15: Completed | E15: LVT & carpet tile flooring | F15: 6.25% | G15: ='Completed - Abington Fam Dental'!F37 | H15: ='Completed - Abington Fam Dental'!F38 | I15: ='Completed - Abington Fam Dental'!F39 | J15: ='Completed - Abington Fam Dental'!F40 | K15: ='Completed - Abington Fam Dental'!F41 | L15: ='Completed - Abington Fam Dental'!F42
B16: 3 | C16: Gentle Dental Peabody | D16: Completed | E16: LVT & carpet tile flooring | F16: 6.25% | G16: ='Completed - GD Peabody'!F36 | H16: ='Completed - GD Peabody'!F37 | I16: ='Completed - GD Peabody'!F38 | J16: ='Completed - GD Peabody'!F39 | K16: ='Completed - GD Peabody'!F40 | L16: ='Completed - GD Peabody'!F41
B17: 4 | C17: Portland Dental | D17: Completed | E17: LVT flooring | F17: 5.5% | G17: ='Completed - Portland Dental'!F28 | H17: ='Completed - Portland Dental'!F29 | I17: ='Completed - Portland Dental'!F30 | J17: ='Completed - Portland Dental'!F31 | K17: ='Completed - Portland Dental'!F32 | L17: ='Completed - Portland Dental'!F33
B18: 5 | C18: Natick Gentle Dental | D18: Completed | E18: LVT flooring | F18: 6.25% | G18: ='Completed - GD Natick'!F30 | H18: ='Completed - GD Natick'!F31 | I18: ='Completed - GD Natick'!F32 | J18: ='Completed - GD Natick'!F33 | K18: ='Completed - GD Natick'!F34 | L18: ='Completed - GD Natick'!F35
B19: 6 | C19: Medford Office — Labor + install materials | D19: Completed | E19: LVT & carpet tile flooring | F19: 6.25% | G19: ='Completed - Medford'!F26 | H19: ='Completed - Medford'!F27 | I19: – | J19: ='Completed - Medford'!F28 | K19: ='Completed - Medford'!F29 | L19: ='Completed - Medford'!F30
B20: 7 | C20: Willimantic Dental | D20: Completed | E20: Broadloom carpet flooring | F20: 6.35% | G20: ='Completed - Willimantic Dental'!F29 | H20: ='Completed - Willimantic Dental'!F30 | I20: ='Completed - Willimantic Dental'!F31 | J20: ='Completed - Willimantic Dental'!F32 | K20: ='Completed - Willimantic Dental'!F33 | L20: ='Completed - Willimantic Dental'!F34
B21: 8 | C21: Canton Dental | D21: In process | E21: Carpet tile flooring | F21: 6.25% | G21: ='In Process - Canton Dental'!F28 | H21: ='In Process - Canton Dental'!F29 | I21: ='In Process - Canton Dental'!F30 | J21: ='In Process - Canton Dental'!F31 | K21: ='In Process - Canton Dental'!F32 | L21: ='In Process - Canton Dental'!F33
B22: 9 | C22: Rochester Gentle Dental | D22: In process | E22: LVT & carpet tile flooring | F22: 0% | G22: ='In Process - GD Rochester'!F31 | H22: ='In Process - GD Rochester'!F32 | I22: ='In Process - GD Rochester'!F33 | J22: ='In Process - GD Rochester'!F34 | K22: ='In Process - GD Rochester'!F35 | L22: ='In Process - GD Rochester'!F36
B23: 10 | C23: Quincy Carpet Tile | D23: Proposal | E23: Carpet tile flooring | F23: 6.25% | G23: ='Quincy Carpet Tile'!F28 | H23: ='Quincy Carpet Tile'!F29 | I23: ='Quincy Carpet Tile'!F30 | J23: ='Quincy Carpet Tile'!F31 | K23: ='Quincy Carpet Tile'!F32 | L23: ='Quincy Carpet Tile'!F33
B24: 11 | C24: Sunrise Family Dental | D24: Needs revisit | E24: LVT & carpet tile flooring | F24: 6.35% | G24: ='Sunrise Family Dental'!F39 | H24: ='Sunrise Family Dental'!F40 | I24: ='Sunrise Family Dental'!F41 | J24: ='Sunrise Family Dental'!F42 | K24: ='Sunrise Family Dental'!F43 | L24: ='Sunrise Family Dental'!F44
B25: 12 | C25: Chelmsford Office | D25: Proposal | E25: Carpet tile flooring | F25: 6.25% | G25: ='Chelmsford Office'!F28 | H25: ='Chelmsford Office'!F29 | I25: ='Chelmsford Office'!F30 | J25: ='Chelmsford Office'!F31 | K25: ='Chelmsford Office'!F32 | L25: ='Chelmsford Office'!F33
B26: 13 | C26: Meriden Dental | D26: Proposal | E26: LVT & carpet tile flooring | F26: 6.35% | G26: ='Meriden Dental'!F36 | H26: ='Meriden Dental'!F37 | I26: ='Meriden Dental'!F38 | J26: ='Meriden Dental'!F39 | K26: ='Meriden Dental'!F40 | L26: ='Meriden Dental'!F41
B27: 14 | C27: Family Dental Newington | D27: Proposal | E27: Carpet tile flooring | F27: 6.35% | G27: ='Family Dental Newington'!F30 | H27: ='Family Dental Newington'!F31 | I27: ='Family Dental Newington'!F32 | J27: ='Family Dental Newington'!F33 | K27: ='Family Dental Newington'!F34 | L27: ='Family Dental Newington'!F35
B28: 15 | C28: New Haven Dental — Flooring | D28: Proposal | E28: LVT & carpet tile flooring | F28: 6.35% | G28: ='New Haven Dental Flooring'!F34 | H28: ='New Haven Dental Flooring'!F35 | I28: ='New Haven Dental Flooring'!F36 | J28: ='New Haven Dental Flooring'!F37 | K28: ='New Haven Dental Flooring'!F38 | L28: ='New Haven Dental Flooring'!F39
B29: 16 | C29: New Haven Dental — Painting | D29: Proposal | E29: Painting & wallpaper removal | F29: – | G29: – | H29: – | I29: – | J29: – | K29: ='New Haven Dental Painting'!F16 | L29: ='New Haven Dental Painting'!F17
B30: 17 | C30: Medford Office — Full (materials + labor) | D30: Proposal | E30: LVT & carpet tile flooring | F30: 6.25% | G30: ='Medford - Full (Mat + Labor)'!F31 | H30: ='Medford - Full (Mat + Labor)'!F32 | I30: ='Medford - Full (Mat + Labor)'!F33 | J30: ='Medford - Full (Mat + Labor)'!F34 | K30: ='Medford - Full (Mat + Labor)'!F35 | L30: ='Medford - Full (Mat + Labor)'!F36
B31: 18 | C31: Great Hill Dental — Partial (465 SF) | D31: Proposal | E31: LVT flooring | F31: 6.25% | G31: ='Great Hill Dental - Partial'!F29 | H31: ='Great Hill Dental - Partial'!F30 | I31: ='Great Hill Dental - Partial'!F31 | J31: ='Great Hill Dental - Partial'!F32 | K31: ='Great Hill Dental - Partial'!F33 | L31: ='Great Hill Dental - Partial'!F34
B32: 19 | C32: Great Hill Dental — Full LVP (2,818 SF) | D32: Proposal | E32: LVT flooring | F32: 6.25% | G32: ='Great Hill Dental Full LVP'!F30 | H32: ='Great Hill Dental Full LVP'!F31 | I32: ='Great Hill Dental Full LVP'!F32 | J32: ='Great Hill Dental Full LVP'!F33 | K32: ='Great Hill Dental Full LVP'!F34 | L32: ='Great Hill Dental Full LVP'!F35
B33: 20 | C33: Dental Care Associates Selinsgrove | D33: Proposal | E33: LVT & carpet tile flooring | F33: Included | G33: ='Selinsgrove'!F34 | H33: ='Selinsgrove'!F35 | I33: ='Selinsgrove'!F36 | J33: – | K33: ='Selinsgrove'!F38 | L33: ='Selinsgrove'!F39
C34: TOTAL | G34: =SUM(G14:G33) | H34: =SUM(H14:H33) | I34: =SUM(I14:I33) | J34: =SUM(J14:J33) | K34: =SUM(K14:K33) | L34: =SUM(L14:L33)
B36: Status legend: Completed = installed and closed out · In process = approved and scheduled · Proposal = issued, awaiting approval · Needs revisit = draft pricing to be reconfirmed before issue. Tax is charged on materials only at the state rate shown; freight and labor are untaxed. Selinsgrove (PA) pricing is inclusive of Pennsylvania sales & use tax. Deposits are 50% of the proposal total, due on approval.
B38: Dynamic Home Solutions (DHS) · Prepared for 42 North · Proposal names link to their detailed tabs

Sheet Completed - GD Braintree
B3: 42 NORTH | RETAIL FLOORING PROPOSAL | F3: COMPLETED
B4: Gentle Dental Braintree
B5: LVT & carpet tile flooring
C7: PREPARED BY | D7: TAX BASIS | F7: PROPOSAL TOTAL
C8: Dynamic Home Solutions (DHS) | D8: 6.25% on materials | F8: =F38
B10: # | C10: DESCRIPTION | D10: QTY | E10: UNIT PRICE | F10: LINE TOTAL
C11: LABOR
B12: 1 | C12: Install LVT | D12: 1404 | E12: 2.1 | F12: =D12*E12
B13: 2 | C13: Install Carpet Tile | D13: 959 | E13: 0.95 | F13: =D13*E13
B14: 3 | C14: Rip/Haul – Carpet | D14: 861 | E14: 0.45 | F14: =D14*E14
B15: 4 | C15: Rip/Haul – Floating | D15: 1272 | E15: 0.75 | F15: =D15*E15
B16: 5 | C16: Rip/Haul – Glue Down | D16: 1272 | E16: 1.45 | F16: =D16*E16
B17: 6 | C17: Self-Level/Prep | D17: 1272 | E17: 1.19 | F17: =D17*E17
B18: 7 | C18: Night and Weekend | D18: 1 | E18: 700 | F18: =D18*E18
B19: 8 | C19: Install Cove Base | D19: 850 | E19: 1.1 | F19: =D19*E19
B20: 9 | C20: Furniture Moving | D20: 16 | E20: 150 | F20: =D20*E20
C22: MATERIALS
B23: 10 | C23: Mannington Spacia LVT | D23: 1404 | E23: 2.35 | F23: =D23*E23
B24: 11 | C24: MoistureLoc | D24: 4 | E24: 199 | F24: =D24*E24
B25: 12 | C25: Mannington Carpet Tile Style – Silhouette Color-Bonds | D25: 958.5 | E25: 3.95 | F25: =D25*E25
B26: 13 | C26: Mannington Infinity II Pressure Sensitive Adhesives | D26: 1 | E26: 179.5 | F26: =D26*E26
B27: 14 | C27: Self-Leveler Mapei HFL and Proma Pro Patch Supreme | D27: 35 | E27: 27 | F27: =D27*E27
B28: 15 | C28: 4" Cove Base 1/8" – customer to select color | D28: 850 | E28: 1.15 | F28: =D28*E28
B29: 16 | C29: Rubber T-caps – customer to select color | D29: 7 | E29: 32 | F29: =D29*E29
C31: FREIGHT & DISTRIBUTION
B32: 17 | C32: Freight | D32: 1 | E32: 430 | F32: =D32*E32
C34: Labor subtotal | F34: =SUM(F12:F20)
C35: Materials subtotal | F35: =SUM(F23:F29)
C36: Freight & distribution | F36: =SUM(F32)
C37: Tax on materials | E37: 0.0625 | F37: =F35*E37
C38: TOTAL | F38: =F34+F35+F36+F37
C39: Deposit due on approval | E39: 0.5 | F39: =F38*E39
C40: Balance due on completion | F40: =F38-F39
B42: PROJECT NOTES, TERMS & CUSTOMER RESPONSIBILITIES
C44: Estimate validity & schedule
B45: • | C45: This estimate is valid for 30 days from the date issued.
B46: • | C46: Product lead time is estimated at 3–6 weeks from approval/order placement (lead times can change).
C48: Payment terms
B49: • | C49: 50% deposit due upfront to release materials and secure scheduling.
B50: • | C50: Remaining balance due upon project completion (final walk-through/substantial completion).
C52: Subfloor & floor prep
B53: • | C53: Floor prep (self-leveling/skim/patch) is included as listed in the line items.
B54: • | C54: Any additional prep required after demo (patching/skim-coating/self-leveling beyond what's included) will be reviewed with the customer and priced as an approved change before proceeding.
B55: • | C55: If moisture issues are discovered, moisture mitigation will be reviewed and priced as an approved change before proceeding.
C57: Work hours & access
B58: • | C58: Estimate accounts for work performed at night and/or over weekends as listed in the scope.
B59: • | C59: Customer to provide site access during scheduled work hours and ensure DHS can work without interruption.
C61: Fixed items
B62: • | C62: DHS will do its best to install neatly around fixed items where removal is not possible.
C64: Customer responsibilities (prior to start of work)
B65: • | C65: Clear access: all areas in scope must be cleared of loose items prior to installation unless included as a line item.
B66: • | C66: Remove/secure electronics, boxes, small items, breakables, and personal belongings from all work areas.
B67: • | C67: Utilities: customer/GC to provide power, lighting, and HVAC as needed for installation.
B68: • | C68: Site logistics: customer/GC to coordinate parking/loading access and access cards/keys.
C70: Dental chairs & equipment
B71: • | C71: Customer is responsible for having dental chair control units and/or equipment attachments disconnected/removed so chairs can be safely moved for installation access.
B72: • | C72: DHS will take reasonable care to protect chairs/equipment but is not responsible for their proper functioning or operation after installation.
B73: • | C73: If chairs/equipment are not properly disconnected at the scheduled start, DHS may pause, reschedule, and/or bill additional labor for delays.
C75: Warranty & cancellations
B76: • | C76: DHS provides a one-year labor warranty on workmanship (see one-pager).
B77: • | C77: Manufacturer warranties apply separately for materials.
B78: • | C78: If the customer cancels or changes product selection after materials are ordered, manufacturer restocking fees and any freight/return costs may apply.
C80: Insurance
B81: • | C81: DHS can provide a Certificate of Insurance upon request.
C83: Exclusions / add-ons
B84: • | C84: Please review the floor plan/scope areas and notify DHS of any discrepancies prior to deposit being initiated.
B85: • | C85: Change orders: any additional work or scope changes must be approved in writing prior to proceeding.

Sheet Completed - Abington Fam Dental
B3: 42 NORTH | RETAIL FLOORING PROPOSAL | F3: COMPLETED
B4: Abington Family Dental
B5: LVT & carpet tile flooring
C7: PREPARED BY | D7: TAX BASIS | F7: PROPOSAL TOTAL
C8: Dynamic Home Solutions (DHS) | D8: 6.25% on materials | F8: =F41
B10: # | C10: DESCRIPTION | D10: QTY | E10: UNIT PRICE | F10: LINE TOTAL
C11: LABOR
B12: 1 | C12: Install LVT | D12: 3216 | E12: 2.1 | F12: =D12*E12
B13: 2 | C13: Install Carpet Tile | D13: 2121 | E13: 0.95 | F13: =D13*E13
B14: 3 | C14: Rip/Haul – Carpet | D14: 1928 | E14: 0.45 | F14: =D14*E14
B15: 4 | C15: Grind Subfloor | D15: 500 | E15: 1.25 | F15: =D15*E15
B16: 5 | C16: Rip/Haul – Glue Down | D16: 2911 | E16: 1.45 | F16: =D16*E16
B17: 6 | C17: Self-Level/Prep | D17: 2911 | E17: 1.02 | F17: =D17*E17
B18: 7 | C18: Apply Moisture Mitigation | D18: 500 | E18: 0.75 | F18: =D18*E18
B19: 8 | C19: Night and Weekend | D19: 2 | E19: 700 | F19: =D19*E19
B20: 9 | C20: Install Cove Base | D20: 1750 | E20: 1.1 | F20: =D20*E20
B21: 10 | C21: Furniture Moving | D21: 21 | E21: 150 | F21: =D21*E21
C23: MATERIALS
B24: 11 | C24: Mannington Spacia LVT Nordic Oak | D24: 3216 | E24: 2.35 | F24: =D24*E24
B25: 12 | C25: Mapei 399 | D25: 8 | E25: 199 | F25: =D25*E25
B26: 13 | C26: Mapei Planiseal Max | D26: 1 | E26: 370 | F26: =D26*E26
B27: 14 | C27: Mannington Carpet Tile Style – Silhouette Color-Bonds | D27: 2121 | E27: 3.95 | F27: =D27*E27
B28: 15 | C28: Mannington Infinity II Pressure Sensitive Adhesives | D28: 3 | E28: 179.5 | F28: =D28*E28
B29: 16 | C29: Mannington Assure Sealer | D29: 3 | E29: 228.5 | F29: =D29*E29
B30: 17 | C30: Leveler/Prep Materials | D30: 2911 | E30: 0.85 | F30: =D30*E30
B31: 18 | C31: 4" Cove Base 1/8" – customer to select color | D31: 1750 | E31: 1.15 | F31: =D31*E31
B32: 19 | C32: Rubber T-caps – customer to select color | D32: 11 | E32: 32 | F32: =D32*E32
C34: FREIGHT & DISTRIBUTION
B35: 20 | C35: Freight | D35: 1 | E35: 492.5 | F35: =D35*E35
C37: Labor subtotal | F37: =SUM(F12:F21)
C38: Materials subtotal | F38: =SUM(F24:F32)
C39: Freight & distribution | F39: =SUM(F35)
C40: Tax on materials | E40: 0.0625 | F40: =F38*E40
C41: TOTAL | F41: =F37+F38+F39+F40
C42: Deposit due on approval | E42: 0.5 | F42: =F41*E42
C43: Balance due on completion | F43: =F41-F42
B45: PROJECT NOTES, TERMS & CUSTOMER RESPONSIBILITIES
C47: Estimate validity & schedule
B48: • | C48: This estimate is valid for 30 days from the date issued.
B49: • | C49: Product lead time is estimated at 3–6 weeks from approval/order placement (lead times can change).
C51: Payment terms
B52: • | C52: 50% deposit due upfront to release materials and secure scheduling.
B53: • | C53: Remaining balance due upon project completion (final walk-through/substantial completion).
C55: Subfloor & floor prep
B56: • | C56: Floor prep (self-leveling/skim/patch) is included as listed in the line items.
B57: • | C57: Any additional prep required after demo (patching/skim-coating/self-leveling beyond what's included) will be reviewed with the customer and priced as an approved change before proceeding.
B58: • | C58: Subfloor grinding and moisture mitigation are included as listed in the line items; if additional areas are found to have moisture issues, additional charges will apply.
C60: Work hours & access
B61: • | C61: Estimate accounts for work performed at night and/or over weekends as listed in the scope.
B62: • | C62: Customer to provide site access during scheduled work hours and ensure DHS can work without interruption.
C64: Fixed items
B65: • | C65: DHS will do its best to install neatly around fixed items where removal is not possible.
C67: Customer responsibilities (prior to start of work)
B68: • | C68: Clear access: all areas in scope must be cleared of loose items prior to installation unless included as a line item.
B69: • | C69: Remove/secure electronics, boxes, small items, breakables, and personal belongings from all work areas.
B70: • | C70: Utilities: customer/GC to provide power, lighting, and HVAC as needed for installation.
B71: • | C71: Site logistics: customer/GC to coordinate parking/loading access and access cards/keys.
C73: Dental chairs & equipment
B74: • | C74: Customer is responsible for having dental chair control units and/or equipment attachments disconnected/removed so chairs can be safely moved for installation access.
B75: • | C75: DHS will take reasonable care to protect chairs/equipment but is not responsible for their proper functioning or operation after installation.
B76: • | C76: If chairs/equipment are not properly disconnected at the scheduled start, DHS may pause, reschedule, and/or bill additional labor for delays.
C78: Warranty & cancellations
B79: • | C79: DHS provides a one-year labor warranty on workmanship (see one-pager).
B80: • | C80: Manufacturer warranties apply separately for materials.
B81: • | C81: If the customer cancels or changes product selection after materials are ordered, manufacturer restocking fees and any freight/return costs may apply.
C83: Insurance
B84: • | C84: DHS can provide a Certificate of Insurance upon request.
C86: Exclusions / add-ons
B87: • | C87: Please review the floor plan/scope areas and notify DHS of any discrepancies prior to deposit being initiated.
B88: • | C88: Change orders: any additional work or scope changes must be approved in writing prior to proceeding.

Sheet Completed - GD Peabody
B3: 42 NORTH | RETAIL FLOORING PROPOSAL | F3: COMPLETED
B4: Gentle Dental Peabody
B5: LVT & carpet tile flooring
C7: PREPARED BY | D7: TAX BASIS | F7: PROPOSAL TOTAL
C8: Dynamic Home Solutions (DHS) | D8: 6.25% on materials | F8: =F40
B10: # | C10: DESCRIPTION | D10: QTY | E10: UNIT PRICE | F10: LINE TOTAL
C11: LABOR
B12: 1 | C12: Install LVT | D12: 2610 | E12: 2.1 | F12: =D12*E12
B13: 2 | C13: Install Carpet Tile | D13: 640 | E13: 0.95 | F13: =D13*E13
B14: 3 | C14: Rip/Haul – Carpet | D14: 562 | E14: 0.45 | F14: =D14*E14
B15: 4 | C15: Rip/Haul – Glue Down | D15: 2372 | E15: 1.45 | F15: =D15*E15
B16: 5 | C16: Install Ultraply | D16: 2560 | E16: 1.45 | F16: =D16*E16
B17: 6 | C17: Self-Level/Prep | D17: 2372 | E17: 1.03 | F17: =D17*E17
B18: 7 | C18: Night and Weekend | D18: 4 | E18: 700 | F18: =D18*E18
B19: 8 | C19: Install Cove Base | D19: 1204 | E19: 1.1 | F19: =D19*E19
B20: 9 | C20: Furniture Moving | D20: 20 | E20: 150 | F20: =D20*E20
C22: MATERIALS
B23: 10 | C23: Mannington Spacia LVT Nordic Oak | D23: 2653.5 | E23: 2.35 | F23: =D23*E23
B24: 11 | C24: MoistureLoc LVT Adhesive | D24: 7 | E24: 199 | F24: =D24*E24
B25: 12 | C25: Mannington Carpet Tile Style – Silhouette Color-Bonds | D25: 640 | E25: 3.95 | F25: =D25*E25
B26: 13 | C26: Mannington Infinity II Pressure Sensitive Adhesives | D26: 1 | E26: 179.5 | F26: =D26*E26
B27: 14 | C27: Mannington Assure Sealer | D27: 1 | E27: 228.5 | F27: =D27*E27
B28: 15 | C28: Ultraply | D28: 80 | E28: 34 | F28: =D28*E28
B29: 16 | C29: Leveler/Prep Materials | D29: 2372 | E29: 0.95 | F29: =D29*E29
B30: 17 | C30: 4" Cove Base 1/8" – customer to select color | D30: 1204 | E30: 1.21 | F30: =D30*E30
B31: 18 | C31: Rubber T-caps and stairnose (1) – customer to select color | D31: 12 | E31: 32 | F31: =D31*E31
C33: FREIGHT & DISTRIBUTION
B34: 19 | C34: Freight | D34: 1 | E34: 492.5 | F34: =D34*E34
C36: Labor subtotal | F36: =SUM(F12:F20)
C37: Materials subtotal | F37: =SUM(F23:F31)
C38: Freight & distribution | F38: =SUM(F34)
C39: Tax on materials | E39: 0.0625 | F39: =F37*E39
C40: TOTAL | F40: =F36+F37+F38+F39
C41: Deposit due on approval | E41: 0.5 | F41: =F40*E41
C42: Balance due on completion | F42: =F40-F41
B44: PROJECT NOTES, TERMS & CUSTOMER RESPONSIBILITIES
C46: Source: Dynamic Home Solutions (DHS) Estimate 4326-1, dated 4/3/2026
C47: Estimate validity & schedule
B48: • | C48: This estimate is valid for 30 days from the date issued.
B49: • | C49: Product lead time is estimated at 3–6 weeks from approval/order placement (lead times can change).
B50: • | C50: Estimated on-site duration is 4–8 working days, assuming areas are ready and materials are on site; may vary based on final phasing.
C52: Payment terms
B53: • | C53: 50% deposit due upfront to release materials and secure scheduling.
B54: • | C54: Remaining balance due upon project completion (final walk-through/substantial completion).
C56: Subfloor & floor prep
B57: • | C57: Existing subfloor appears to be gypcrete/softcrete (lightweight gypsum); during removal of glued-down flooring this material can fracture and may require additional prep.
B58: • | C58: Medium floor prep (scrape and patch) is included.
B59: • | C59: Any additional prep after demo (patching/skim-coating/self-leveling beyond what's included) will be reviewed with the customer and priced as an approved change before proceeding.
B60: • | C60: Quote is figured to hand-grind Exam (Office) Rooms 4, 5, and 6 plus Hall 6, applying two coats of moisture mitigation.
B61: • | C61: If additional areas have moisture issues, additional charges apply at a minimum of $2.75/sf; a large number of offices may require a grinding machine rental at $3,000 per day.
C63: Work hours & access
B64: • | C64: Estimate accounts for work performed at night and/or over two weekends as listed in the scope.
B65: • | C65: Customer to provide site access during scheduled work hours and ensure DHS can work without interruption.
C67: Fixed items
B68: • | C68: DHS will do its best to install neatly around fixed items where removal is not possible.
C70: Customer responsibilities (prior to start of work)
B71: • | C71: Clear access: all areas in scope must be cleared of loose items prior to installation unless included as a line item.
B72: • | C72: Remove/secure electronics, boxes, small items, breakables, and personal belongings from all work areas.
B73: • | C73: Utilities: customer/GC to provide power, lighting, and HVAC as needed for installation.
B74: • | C74: Site logistics: customer/GC to coordinate parking/loading access and access cards/keys.
C76: Dental chairs & equipment
B77: • | C77: Customer is responsible for having dental chair control units and/or equipment attachments disconnected/removed so chairs can be safely moved for installation access.
B78: • | C78: DHS will take reasonable care to protect chairs/equipment but is not responsible for their proper functioning or operation after installation.
B79: • | C79: If chairs/equipment are not properly disconnected at the scheduled start, DHS may pause, reschedule, and/or bill additional labor for delays.
C81: Warranty & cancellations
B82: • | C82: DHS provides a one-year labor warranty on workmanship (see one-pager).
B83: • | C83: Manufacturer warranties apply separately for materials.
B84: • | C84: If the customer cancels or changes product selection after materials are ordered, manufacturer restocking fees and any freight/return costs may apply.
C86: Insurance
B87: • | C87: DHS can provide a Certificate of Insurance upon request.
C89: Exclusions / add-ons
B90: • | C90: Review floor plan and confirm areas: blue = glue-down LVT, orange = glue-down carpet tile; notify DHS of any discrepancies prior to deposit.
B91: • | C91: Change orders: any additional work or scope changes must be approved in writing prior to proceeding.

Sheet Completed - Portland Dental
B3: 42 NORTH | RETAIL FLOORING PROPOSAL | F3: COMPLETED
B4: Portland Dental
B5: LVT flooring
C7: PREPARED BY | D7: TAX BASIS | F7: PROPOSAL TOTAL
C8: Dynamic Home Solutions (DHS) | D8: 5.5% on materials | F8: =F32
B10: # | C10: DESCRIPTION | D10: QTY | E10: UNIT PRICE | F10: LINE TOTAL
C11: LABOR
B12: 1 | C12: Install LVT | D12: 159 | E12: 2.65 | F12: =D12*E12
B13: 2 | C13: Skim Coat | D13: 138 | E13: 0.8 | F13: =D13*E13
B14: 3 | C14: Install Cove Base | D14: 54 | E14: 1.1 | F14: =D14*E14
B15: 4 | C15: Furniture | D15: 1 | E15: 175 | F15: =D15*E15
B16: 5 | C16: Night and Weekend | D16: 1 | E16: 700 | F16: =D16*E16
C18: MATERIALS
B19: 6 | C19: Altro Lavencia | D19: 180 | E19: 4.59 | F19: =D19*E19
B20: 7 | C20: Ecofix | D20: 1 | E20: 130 | F20: =D20*E20
B21: 8 | C21: Patch | D21: 4 | E21: 27 | F21: =D21*E21
B22: 9 | C22: 4" Cove Base 1/8" – customer to select color | D22: 54 | E22: 1.15 | F22: =D22*E22
B23: 10 | C23: Rubber T-caps – customer to select color | D23: 1 | E23: 32 | F23: =D23*E23
C25: FREIGHT & DISTRIBUTION
B26: 11 | C26: Freight | D26: 1 | E26: 167.5 | F26: =D26*E26
C28: Labor subtotal | F28: =SUM(F12:F16)
C29: Materials subtotal | F29: =SUM(F19:F23)
C30: Freight & distribution | F30: =SUM(F26)
C31: Tax on materials | E31: 0.055 | F31: =F29*E31
C32: TOTAL | F32: =F28+F29+F30+F31
C33: Deposit due on approval | E33: 0.5 | F33: =F32*E33
C34: Balance due on completion | F34: =F32-F33
B36: PROJECT NOTES, TERMS & CUSTOMER RESPONSIBILITIES
C38: Estimate validity & schedule
B39: • | C39: This estimate is valid for 30 days from the date issued.
B40: • | C40: Product lead time is estimated at 3–6 weeks from approval/order placement (lead times can change).
C42: Payment terms
B43: • | C43: 50% deposit due upfront to release materials and secure scheduling.
B44: • | C44: Remaining balance due upon project completion (final walk-through/substantial completion).
C46: Subfloor & floor prep
B47: • | C47: Floor prep (self-leveling/skim/patch) is included as listed in the line items.
B48: • | C48: Any additional prep required beyond what's included will be reviewed with the customer and priced as an approved change before proceeding.
B49: • | C49: If moisture issues are discovered, moisture mitigation will be reviewed and priced as an approved change before proceeding.
C51: Work hours & access
B52: • | C52: Estimate accounts for work performed at night and/or over weekends as listed in the scope.
B53: • | C53: Customer to provide site access during scheduled work hours and ensure DHS can work without interruption.
C55: Fixed items
B56: • | C56: DHS will do its best to install neatly around fixed items where removal is not possible.
C58: Customer responsibilities (prior to start of work)
B59: • | C59: Clear access: all areas in scope must be cleared of loose items prior to installation unless included as a line item.
B60: • | C60: Remove/secure electronics, boxes, small items, breakables, and personal belongings from all work areas.
B61: • | C61: Utilities: customer/GC to provide power, lighting, and HVAC as needed for installation.
B62: • | C62: Site logistics: customer/GC to coordinate parking/loading access and access cards/keys.
C64: Dental chairs & equipment
B65: • | C65: Customer is responsible for having dental chair control units and/or equipment attachments disconnected/removed so chairs can be safely moved for installation access.
B66: • | C66: DHS will take reasonable care to protect chairs/equipment but is not responsible for their proper functioning or operation after installation.
B67: • | C67: If chairs/equipment are not properly disconnected at the scheduled start, DHS may pause, reschedule, and/or bill additional labor for delays.
C69: Warranty & cancellations
B70: • | C70: DHS provides a one-year labor warranty on workmanship (see one-pager).
B71: • | C71: Manufacturer warranties apply separately for materials.
B72: • | C72: If the customer cancels or changes product selection after materials are ordered, manufacturer restocking fees and any freight/return costs may apply.
C74: Insurance
B75: • | C75: DHS can provide a Certificate of Insurance upon request.
C77: Exclusions / add-ons
B78: • | C78: Please review the floor plan/scope areas and notify DHS of any discrepancies prior to deposit being initiated.
B79: • | C79: Change orders: any additional work or scope changes must be approved in writing prior to proceeding.

Sheet Completed - GD Natick
B3: 42 NORTH | RETAIL FLOORING PROPOSAL | F3: COMPLETED
B4: Natick Gentle Dental
B5: LVT flooring — Section 1
C7: PREPARED BY | D7: TAX BASIS | F7: PROPOSAL TOTAL
C8: Dynamic Home Solutions (DHS) | D8: 6.25% on materials | F8: =F34
B10: # | C10: DESCRIPTION | D10: QTY | E10: UNIT PRICE | F10: LINE TOTAL
C11: LABOR
B12: 1 | C12: Install LVT | D12: 172 | E12: 2.1 | F12: =D12*E12
B13: 2 | C13: Rip/Haul – Glue Down | D13: 140 | E13: 1.45 | F13: =D13*E13
B14: 3 | C14: Rip/Haul – Glue Down | D14: 140 | E14: lump sum | F14: 225
B15: 4 | C15: Skim Coat | D15: 172 | E15: 1 | F15: =D15*E15
B16: 5 | C16: Install Cove Base | D16: 72 | E16: 1.1 | F16: =D16*E16
B17: 6 | C17: Toilets | D17: 2 | E17: 150 | F17: =D17*E17
C19: MATERIALS
B20: 7 | C20: Altro Lavencia | D20: 180 | E20: 4.59 | F20: =D20*E20
B21: 8 | C21: Ecofix | D21: 1 | E21: 130 | F21: =D21*E21
B22: 9 | C22: Patch | D22: 4 | E22: 27 | F22: =D22*E22
B23: 10 | C23: 4" Cove Base 1/8" – customer to select color | D23: 72 | E23: 1.15 | F23: =D23*E23
B24: 11 | C24: Wax Ring and Supply Line | D24: 1 | E24: 45 | F24: =D24*E24
B25: 12 | C25: Rubber T-caps – customer to select color | D25: 1 | E25: 32 | F25: =D25*E25
C27: FREIGHT & DISTRIBUTION
B28: 13 | C28: Mannington Freight | D28: 1 | E28: 167.5 | F28: =D28*E28
C30: Labor subtotal | F30: =SUM(F12:F17)
C31: Materials subtotal | F31: =SUM(F20:F25)
C32: Freight & distribution | F32: =SUM(F28)
C33: Tax on materials | E33: 0.0625 | F33: =F31*E33
C34: TOTAL | F34: =F30+F31+F32+F33
C35: Deposit due on approval | E35: 0.5 | F35: =F34*E35
C36: Balance due on completion | F36: =F34-F35
B38: PROJECT NOTES, TERMS & CUSTOMER RESPONSIBILITIES
C40: Estimate validity & schedule
B41: • | C41: This estimate is valid for 30 days from the date issued.
B42: • | C42: Product lead time is estimated at 3–6 weeks from approval/order placement (lead times can change).
C44: Payment terms
B45: • | C45: 50% deposit due upfront to release materials and secure scheduling.
B46: • | C46: Remaining balance due upon project completion (final walk-through/substantial completion).
C48: Subfloor & floor prep
B49: • | C49: Floor prep (self-leveling/skim/patch) is included as listed in the line items.
B50: • | C50: Any additional prep required after demo (patching/skim-coating/self-leveling beyond what's included) will be reviewed with the customer and priced as an approved change before proceeding.
B51: • | C51: If moisture issues are discovered, moisture mitigation will be reviewed and priced as an approved change before proceeding.
C53: Work hours & access
B54: • | C54: Customer to provide site access during scheduled work hours and ensure DHS can work without interruption.
C56: Fixed items
B57: • | C57: DHS will do its best to install neatly around fixed items where removal is not possible.
C59: Customer responsibilities (prior to start of work)
B60: • | C60: Clear access: all areas in scope must be cleared of loose items prior to installation unless included as a line item.
B61: • | C61: Remove/secure electronics, boxes, small items, breakables, and personal belongings from all work areas.
B62: • | C62: Utilities: customer/GC to provide power, lighting, and HVAC as needed for installation.
B63: • | C63: Site logistics: customer/GC to coordinate parking/loading access and access cards/keys.
C65: Dental chairs & equipment
B66: • | C66: Customer is responsible for having dental chair control units and/or equipment attachments disconnected/removed so chairs can be safely moved for installation access.
B67: • | C67: DHS will take reasonable care to protect chairs/equipment but is not responsible for their proper functioning or operation after installation.
B68: • | C68: If chairs/equipment are not properly disconnected at the scheduled start, DHS may pause, reschedule, and/or bill additional labor for delays.
C70: Warranty & cancellations
B71: • | C71: DHS provides a one-year labor warranty on workmanship (see one-pager).
B72: • | C72: Manufacturer warranties apply separately for materials.
B73: • | C73: If the customer cancels or changes product selection after materials are ordered, manufacturer restocking fees and any freight/return costs may apply.
C75: Insurance
B76: • | C76: DHS can provide a Certificate of Insurance upon request.
C78: Exclusions / add-ons
B79: • | C79: Please review the floor plan/scope areas and notify DHS of any discrepancies prior to deposit being initiated.
B80: • | C80: Change orders: any additional work or scope changes must be approved in writing prior to proceeding.

Sheet Completed - Medford
B3: 42 NORTH | RETAIL FLOORING PROPOSAL | F3: COMPLETED
B4: Medford Office
B5: LVT & carpet tile flooring — Labor + Install Materials
C7: PREPARED BY | D7: TAX BASIS | F7: PROPOSAL TOTAL
C8: Dynamic Home Solutions (DHS) | D8: 6.25% on materials | F8: =F29
B10: # | C10: DESCRIPTION | D10: QTY | E10: UNIT PRICE | F10: LINE TOTAL
C11: LABOR
B12: 1 | C12: Install LVT (Glue Down – Concrete) | D12: 89 | E12: 2.65 | F12: =D12*E12
B13: 2 | C13: Install Carpet Tile (Glue Down) | D13: 379 | E13: 0.95 | F13: =D13*E13
B14: 3 | C14: Install Cove Base | D14: 157 | E14: 1.1 | F14: =D14*E14
B15: 4 | C15: Skim Coat/Floor Prep (entire floor) | D15: 468 | E15: 0.9 | F15: =D15*E15
B16: 5 | C16: Furniture Moving | D16: 1 | E16: 175 | F16: =D16*E16
B17: 6 | C17: Night/Weekend | D17: 1 | E17: 700 | F17: =D17*E17
B18: 7 | C18: Transport Material (Storage to Install Location) | D18: 1 | E18: 500 | F18: =D18*E18
C20: MATERIALS
B21: 8 | C21: Skim Coat/Leveler | D21: 6 | E21: 34.5 | F21: =D21*E21
B22: 9 | C22: Mapei 399 | D22: 1 | E22: 199 | F22: =D22*E22
B23: 10 | C23: Carpet Tile Adhesive | D23: 1 | E23: 179.5 | F23: =D23*E23
B24: 11 | C24: Rubber T-Mold Transitions | D24: 4 | E24: 32 | F24: =D24*E24
C26: Labor subtotal | F26: =SUM(F12:F18)
C27: Materials subtotal | F27: =SUM(F21:F24)
C28: Tax on materials | E28: 0.0625 | F28: =F27*E28
C29: TOTAL | F29: =F26+F27+F28
C30: Deposit due on approval | E30: 0.5 | F30: =F29*E30
C31: Balance due on completion | F31: =F29-F30
B33: PROJECT NOTES & TERMS
B35: • | C35: 50% deposit due at contract signing; balance due upon completion of work.
B36: • | C36: Pricing valid for 30 days from the proposal date.
B37: • | C37: Quantities are based on field measurements (FloorWizard, 7/10/2026); final billing may adjust to actual installed quantities.
B38: • | C38: Floor prep / skim coat is estimated. If the subfloor requires additional prep once existing flooring is removed, the added prep will be quoted before proceeding.
B39: • | C39: Product colors and selections to be confirmed by customer; pricing may be revised upon final product selection.
B40: • | C40: This proposal covers labor and the listed installation materials only. Finish flooring materials (LVT plank and carpet tile) are supplied by others / by the customer.
C42: DISCLAIMER — CARPET TILE: The new carpet tile will not match the existing carpet tile. Dye lot, color, texture, and style will vary between new and existing material. Customer acknowledges and accepts this visible variation.
B44: FLOOR PLAN / SCOPE AREAS

Sheet Completed - Willimantic Dental
B3: 42 NORTH | RETAIL FLOORING PROPOSAL | F3: COMPLETED
B4: Willimantic Dental
B5: Broadloom carpet flooring
C7: PREPARED BY | D7: TAX BASIS | F7: PROPOSAL TOTAL
C8: Dynamic Home Solutions (DHS) | D8: 6.35% on materials | F8: =F33
B10: # | C10: DESCRIPTION | D10: QTY | E10: UNIT PRICE | F10: LINE TOTAL
C11: LABOR
B12: 1 | C12: Install Broadloom Carpet | D12: 1692 | E12: 0.95 | F12: =D12*E12
B13: 2 | C13: Rip/Haul – Carpet | D13: 1590 | E13: 0.45 | F13: =D13*E13
B14: 3 | C14: Install Walk-off Carpet | D14: 132 | E14: 1.25 | F14: =D14*E14
B15: 4 | C15: Night and Weekend | D15: 1 | E15: 800 | F15: =D15*E15
B16: 5 | C16: Net cut to Baseboard | D16: 316 | E16: 1.5 | F16: =D16*E16
B17: 6 | C17: Furniture Moving | D17: 6 | E17: 150 | F17: =D17*E17
C19: MATERIALS
B20: 7 | C20: Mannington Broadloom Carpet – Precision Color Interval | D20: 1728 | E20: 4.05 | F20: =D20*E20
B21: 8 | C21: Mannington Infinity II Pressure Sensitive Adhesives | D21: 4 | E21: 179.5 | F21: =D21*E21
B22: 9 | C22: Walk-off Mat | D22: 132 | E22: 5.95 | F22: =D22*E22
B23: 10 | C23: Proma 4150 | D23: 1 | E23: 95 | F23: =D23*E23
B24: 11 | C24: Rubber T-caps – customer to select color | D24: 0 | E24: 32 | F24: =D24*E24
C26: FREIGHT & DISTRIBUTION
B27: 12 | C27: Freight & distribution | D27: 1 | E27: 430 | F27: =D27*E27
C29: Labor subtotal | F29: =SUM(F12:F17)
C30: Materials subtotal | F30: =SUM(F20:F24)
C31: Freight & distribution | F31: =SUM(F27)
C32: Tax on materials | E32: 0.0635 | F32: =F30*E32
C33: TOTAL | F33: =F29+F30+F31+F32
C34: Deposit due on approval | E34: 0.5 | F34: =F33*E34
C35: Balance due on completion | F35: =F33-F34
B37: PROJECT NOTES, TERMS & CUSTOMER RESPONSIBILITIES
C39: Estimate validity & schedule
B40: • | C40: This estimate is valid for 30 days from the date issued.
B41: • | C41: Product lead time is estimated at 3–6 weeks from approval/order placement (lead times can change).
C43: Payment terms
B44: • | C44: 50% deposit due upfront to release materials and secure scheduling.
B45: • | C45: Remaining balance due upon project completion (final walk-through/substantial completion).
C47: Subfloor & floor prep
B48: • | C48: Floor prep (self-leveling/skim/patch) is included as listed in the line items.
B49: • | C49: Any additional prep required after demo (patching/skim-coating/self-leveling beyond what's included) will be reviewed with the customer and priced as an approved change before proceeding.
B50: • | C50: If moisture issues are discovered, moisture mitigation will be reviewed and priced as an approved change before proceeding.
C52: Work hours & access
B53: • | C53: Estimate accounts for work performed at night and/or over weekends as listed in the scope.
B54: • | C54: Customer to provide site access during scheduled work hours and ensure DHS can work without interruption.
C56: Fixed items
B57: • | C57: DHS will do its best to install neatly around fixed items where removal is not possible.
C59: Customer responsibilities (prior to start of work)
B60: • | C60: Clear access: all areas in scope must be cleared of loose items prior to installation unless included as a line item.
B61: • | C61: Remove/secure electronics, boxes, small items, breakables, and personal belongings from all work areas.
B62: • | C62: Utilities: customer/GC to provide power, lighting, and HVAC as needed for installation.
B63: • | C63: Site logistics: customer/GC to coordinate parking/loading access and access cards/keys.
C65: Dental chairs & equipment
B66: • | C66: Customer is responsible for having dental chair control units and/or equipment attachments disconnected/removed so chairs can be safely moved for installation access.
B67: • | C67: DHS will take reasonable care to protect chairs/equipment but is not responsible for their proper functioning or operation after installation.
B68: • | C68: If chairs/equipment are not properly disconnected at the scheduled start, DHS may pause, reschedule, and/or bill additional labor for delays.
C70: Warranty & cancellations
B71: • | C71: DHS provides a one-year labor warranty on workmanship (see one-pager).
B72: • | C72: Manufacturer warranties apply separately for materials.
B73: • | C73: If the customer cancels or changes product selection after materials are ordered, manufacturer restocking fees and any freight/return costs may apply.
C75: Insurance
B76: • | C76: DHS can provide a Certificate of Insurance upon request.
C78: Exclusions / add-ons
B79: • | C79: Please review the floor plan/scope areas and notify DHS of any discrepancies prior to deposit being initiated.
B80: • | C80: Change orders: any additional work or scope changes must be approved in writing prior to proceeding.

Sheet In Process - Canton Dental
B3: 42 NORTH | RETAIL FLOORING PROPOSAL | F3: IN PROCESS
B4: Canton Dental
B5: Carpet tile flooring
C7: PREPARED BY | D7: TAX BASIS | F7: PROPOSAL TOTAL
C8: Dynamic Home Solutions (DHS) | D8: 6.25% on materials | F8: =F32
B10: # | C10: DESCRIPTION | D10: QTY | E10: UNIT PRICE | F10: LINE TOTAL
C11: LABOR
B12: 1 | C12: Install Carpet Tile | D12: 794 | E12: 0.95 | F12: =D12*E12
B13: 2 | C13: Rip/Haul – Carpet | D13: 722 | E13: 0.5 | F13: =D13*E13
B14: 3 | C14: Night and Weekend | D14: 1 | E14: 700 | F14: =D14*E14
B15: 4 | C15: Install Cove Base | D15: 285 | E15: 1.1 | F15: =D15*E15
B16: 5 | C16: Furniture Moving | D16: 4 | E16: 150 | F16: =D16*E16
C18: MATERIALS
B19: 6 | C19: Mannington Carpet Tile Style – Silhouette Color-Bonds | D19: 800 | E19: 3.95 | F19: =D19*E19
B20: 7 | C20: Mannington Infinity II Pressure Sensitive Adhesives | D20: 1 | E20: 179.5 | F20: =D20*E20
B21: 8 | C21: Mannington Assure Sealer | D21: 1 | E21: 228.5 | F21: =D21*E21
B22: 9 | C22: 4" Cove Base 1/8" – customer to select color | D22: 286 | E22: 1.35 | F22: =D22*E22
B23: 10 | C23: Rubber T-caps – customer to select color | D23: 4 | E23: 32 | F23: =D23*E23
C25: FREIGHT & DISTRIBUTION
B26: 11 | C26: Freight | D26: 1 | E26: 492.5 | F26: =D26*E26
C28: Labor subtotal | F28: =SUM(F12:F16)
C29: Materials subtotal | F29: =SUM(F19:F23)
C30: Freight & distribution | F30: =SUM(F26)
C31: Tax on materials | E31: 0.0625 | F31: =F29*E31
C32: TOTAL | F32: =F28+F29+F30+F31
C33: Deposit due on approval | E33: 0.5 | F33: =F32*E33
C34: Balance due on completion | F34: =F32-F33
B36: PROJECT NOTES, TERMS & CUSTOMER RESPONSIBILITIES
C38: Estimate validity & schedule
B39: • | C39: This estimate is valid for 30 days from the date issued.
B40: • | C40: Product lead time is estimated at 3–6 weeks from approval/order placement (lead times can change).
C42: Payment terms
B43: • | C43: 50% deposit due upfront to release materials and secure scheduling.
B44: • | C44: Remaining balance due upon project completion (final walk-through/substantial completion).
C46: Subfloor & floor prep
B47: • | C47: Floor prep is not included unless listed as a line item; any prep found to be required after demo will be reviewed with the customer and priced as an approved change before proceeding.
B48: • | C48: If moisture issues are discovered, moisture mitigation will be reviewed and priced as an approved change before proceeding.
C50: Work hours & access
B51: • | C51: Estimate accounts for work performed at night and/or over weekends as listed in the scope.
B52: • | C52: Customer to provide site access during scheduled work hours and ensure DHS can work without interruption.
C54: Fixed items
B55: • | C55: DHS will do its best to install neatly around fixed items where removal is not possible.
C57: Customer responsibilities (prior to start of work)
B58: • | C58: Clear access: all areas in scope must be cleared of loose items prior to installation unless included as a line item.
B59: • | C59: Remove/secure electronics, boxes, small items, breakables, and personal belongings from all work areas.
B60: • | C60: Utilities: customer/GC to provide power, lighting, and HVAC as needed for installation.
B61: • | C61: Site logistics: customer/GC to coordinate parking/loading access and access cards/keys.
C63: Dental chairs & equipment
B64: • | C64: Customer is responsible for having dental chair control units and/or equipment attachments disconnected/removed so chairs can be safely moved for installation access.
B65: • | C65: DHS will take reasonable care to protect chairs/equipment but is not responsible for their proper functioning or operation after installation.
B66: • | C66: If chairs/equipment are not properly disconnected at the scheduled start, DHS may pause, reschedule, and/or bill additional labor for delays.
C68: Warranty & cancellations
B69: • | C69: DHS provides a one-year labor warranty on workmanship (see one-pager).
B70: • | C70: Manufacturer warranties apply separately for materials.
B71: • | C71: If the customer cancels or changes product selection after materials are ordered, manufacturer restocking fees and any freight/return costs may apply.
C73: Insurance
B74: • | C74: DHS can provide a Certificate of Insurance upon request.
C76: Exclusions / add-ons
B77: • | C77: Please review the floor plan/scope areas and notify DHS of any discrepancies prior to deposit being initiated.
B78: • | C78: Change orders: any additional work or scope changes must be approved in writing prior to proceeding.

Sheet In Process - GD Rochester
B3: 42 NORTH | RETAIL FLOORING PROPOSAL | F3: IN PROCESS
B4: Rochester Gentle Dental
B5: LVT & carpet tile flooring
C7: PREPARED BY | D7: TAX BASIS | F7: PROPOSAL TOTAL
C8: Dynamic Home Solutions (DHS) | D8: 0% — New Hampshire | F8: =F35
B10: # | C10: DESCRIPTION | D10: QTY | E10: UNIT PRICE | F10: LINE TOTAL
C11: LABOR
B12: 1 | C12: Install LVT | D12: 910 | E12: 2.1 | F12: =D12*E12
B13: 2 | C13: Install Carpet Tile | D13: 515 | E13: 0.95 | F13: =D13*E13
B14: 3 | C14: Self-Level/skim 1/8" approx | D14: 30 | E14: 43 | F14: =D14*E14
B15: 4 | C15: Night and Weekend | D15: 2 | E15: 700 | F15: =D15*E15
B16: 5 | C16: Install Cove Base | D16: 600 | E16: 1.1 | F16: =D16*E16
C18: MATERIALS
B19: 6 | C19: Mannington Spacia LVT Nordic Oak | D19: 912.5 | E19: 2.35 | F19: =D19*E19
B20: 7 | C20: Mapei 399 | D20: 6 | E20: 199 | F20: =D20*E20
B21: 8 | C21: Mannington Carpet Tile Style – Silhouette Color-Bonds | D21: 576 | E21: 3.95 | F21: =D21*E21
B22: 9 | C22: Mannington Infinity II Pressure Sensitive Adhesives | D22: 1 | E22: 179.5 | F22: =D22*E22
B23: 10 | C23: Mannington Assure Sealer | D23: 1 | E23: 228.5 | F23: =D23*E23
B24: 11 | C24: Leveler/Prep Materials 1/8" approx | D24: 30 | E24: 34.5 | F24: =D24*E24
B25: 12 | C25: 4" Cove Base 1/8" – Burke Charcoal Gray | D25: 600 | E25: 1.35 | F25: =D25*E25
B26: 13 | C26: Rubber T-caps Charcoal Gray | D26: 3 | E26: 32 | F26: =D26*E26
C28: FREIGHT & DISTRIBUTION
B29: 14 | C29: Mannington Freight | D29: 1 | E29: 492.5 | F29: =D29*E29
C31: Labor subtotal | F31: =SUM(F12:F16)
C32: Materials subtotal | F32: =SUM(F19:F26)
C33: Freight & distribution | F33: =SUM(F29)
C34: Tax on materials (NH) | E34: 0 | F34: =F32*E34
C35: TOTAL | F35: =F31+F32+F33+F34
C36: Deposit due on approval | E36: 0.5 | F36: =F35*E36
C37: Balance due on completion | F37: =F35-F36
B39: PROJECT NOTES, TERMS & CUSTOMER RESPONSIBILITIES
C41: Estimate validity & schedule
B42: • | C42: This estimate is valid for 30 days from the date issued.
B43: • | C43: Product lead time is estimated at 3–6 weeks from approval/order placement (lead times can change).
C45: Payment terms
B46: • | C46: 50% deposit due upfront to release materials and secure scheduling.
B47: • | C47: Remaining balance due upon project completion (final walk-through/substantial completion).
C49: Subfloor & floor prep
B50: • | C50: Floor prep (self-leveling/skim/patch) is included as listed in the line items.
B51: • | C51: Any additional prep required beyond what's included will be reviewed with the customer and priced as an approved change before proceeding.
B52: • | C52: If moisture issues are discovered, moisture mitigation will be reviewed and priced as an approved change before proceeding.
C54: Work hours & access
B55: • | C55: Estimate accounts for work performed at night and/or over weekends as listed in the scope.
B56: • | C56: Customer to provide site access during scheduled work hours and ensure DHS can work without interruption.
C58: Fixed items
B59: • | C59: DHS will do its best to install neatly around fixed items where removal is not possible.
C61: Customer responsibilities (prior to start of work)
B62: • | C62: Clear access: all areas in scope must be cleared of loose items prior to installation unless included as a line item.
B63: • | C63: Remove/secure electronics, boxes, small items, breakables, and personal belongings from all work areas.
B64: • | C64: Utilities: customer/GC to provide power, lighting, and HVAC as needed for installation.
B65: • | C65: Site logistics: customer/GC to coordinate parking/loading access and access cards/keys.
C67: Dental chairs & equipment
B68: • | C68: Customer is responsible for having dental chair control units and/or equipment attachments disconnected/removed so chairs can be safely moved for installation access.
B69: • | C69: DHS will take reasonable care to protect chairs/equipment but is not responsible for their proper functioning or operation after installation.
B70: • | C70: If chairs/equipment are not properly disconnected at the scheduled start, DHS may pause, reschedule, and/or bill additional labor for delays.
C72: Warranty & cancellations
B73: • | C73: DHS provides a one-year labor warranty on workmanship (see one-pager).
B74: • | C74: Manufacturer warranties apply separately for materials.
B75: • | C75: If the customer cancels or changes product selection after materials are ordered, manufacturer restocking fees and any freight/return costs may apply.
C77: Insurance
B78: • | C78: DHS can provide a Certificate of Insurance upon request.
C80: Exclusions / add-ons
B81: • | C81: Please review the floor plan/scope areas and notify DHS of any discrepancies prior to deposit being initiated.
B82: • | C82: Change orders: any additional work or scope changes must be approved in writing prior to proceeding.

Sheet Quincy Carpet Tile
B3: 42 NORTH | RETAIL FLOORING PROPOSAL | F3: PROPOSAL
B4: Quincy Carpet Tile
B5: Carpet tile flooring
C7: PREPARED BY | D7: TAX BASIS | F7: PROPOSAL TOTAL
C8: Dynamic Home Solutions (DHS) | D8: 6.25% on materials | F8: =F32
B10: # | C10: DESCRIPTION | D10: QTY | E10: UNIT PRICE | F10: LINE TOTAL
C11: LABOR
B12: 1 | C12: Install Carpet Tile | D12: 1070 | E12: 0.95 | F12: =D12*E12
B13: 2 | C13: Rip/Haul – Carpet | D13: 972 | E13: 0.5 | F13: =D13*E13
B14: 3 | C14: Night and Weekend | D14: 2 | E14: 700 | F14: =D14*E14
B15: 4 | C15: Install Cove Base | D15: 386 | E15: 1.1 | F15: =D15*E15
B16: 5 | C16: Furniture Moving | D16: 5 | E16: 150 | F16: =D16*E16
C18: MATERIALS
B19: 6 | C19: Mannington Carpet Tile Style – Silhouette Color-Bonds | D19: 1086.3 | E19: 3.95 | F19: =D19*E19
B20: 7 | C20: Mannington Infinity II Pressure Sensitive Adhesives | D20: 2 | E20: 179.5 | F20: =D20*E20
B21: 8 | C21: Mannington Assure Sealer | D21: 2 | E21: 228.5 | F21: =D21*E21
B22: 9 | C22: 4" Cove Base 1/8" – customer to select color | D22: 386 | E22: 1.35 | F22: =D22*E22
B23: 10 | C23: Rubber T-caps – customer to select color | D23: 2 | E23: 32 | F23: =D23*E23
C25: FREIGHT & DISTRIBUTION
B26: 11 | C26: Freight | D26: 1 | E26: 492.5 | F26: =D26*E26
C28: Labor subtotal | F28: =SUM(F12:F16)
C29: Materials subtotal | F29: =SUM(F19:F23)
C30: Freight & distribution | F30: =SUM(F26)
C31: Tax on materials | E31: 0.0625 | F31: =F29*E31
C32: TOTAL | F32: =F28+F29+F30+F31
C33: Deposit due on approval | E33: 0.5 | F33: =F32*E33
C34: Balance due on completion | F34: =F32-F33
B36: PROJECT NOTES, TERMS & CUSTOMER RESPONSIBILITIES
C38: Estimate validity & schedule
B39: • | C39: This estimate is valid for 30 days from the date issued.
B40: • | C40: Product lead time is estimated at 3–6 weeks from approval/order placement (lead times can change).
C42: Payment terms
B43: • | C43: 50% deposit due upfront to release materials and secure scheduling.
B44: • | C44: Remaining balance due upon project completion (final walk-through/substantial completion).
C46: Subfloor & floor prep
B47: • | C47: Floor prep is not included unless listed as a line item; any prep found to be required after demo will be reviewed with the customer and priced as an approved change before proceeding.
B48: • | C48: If moisture issues are discovered, moisture mitigation will be reviewed and priced as an approved change before proceeding.
C50: Work hours & access
B51: • | C51: Estimate accounts for work performed at night and/or over weekends as listed in the scope.
B52: • | C52: Customer to provide site access during scheduled work hours and ensure DHS can work without interruption.
C54: Fixed items
B55: • | C55: DHS will do its best to install neatly around fixed items where removal is not possible.
C57: Customer responsibilities (prior to start of work)
B58: • | C58: Clear access: all areas in scope must be cleared of loose items prior to installation unless included as a line item.
B59: • | C59: Remove/secure electronics, boxes, small items, breakables, and personal belongings from all work areas.
B60: • | C60: Utilities: customer/GC to provide power, lighting, and HVAC as needed for installation.
B61: • | C61: Site logistics: customer/GC to coordinate parking/loading access and access cards/keys.
C63: Warranty & cancellations
B64: • | C64: DHS provides a one-year labor warranty on workmanship (see one-pager).
B65: • | C65: Manufacturer warranties apply separately for materials.
B66: • | C66: If the customer cancels or changes product selection after materials are ordered, manufacturer restocking fees and any freight/return costs may apply.
C68: Insurance
B69: • | C69: DHS can provide a Certificate of Insurance upon request.
C71: Exclusions / add-ons
B72: • | C72: Please review the floor plan/scope areas and notify DHS of any discrepancies prior to deposit being initiated.
B73: • | C73: Change orders: any additional work or scope changes must be approved in writing prior to proceeding.

Sheet Sunrise Family Dental
B3: 42 NORTH | RETAIL FLOORING PROPOSAL | F3: NEEDS REVISIT
B4: Sunrise Family Dental
B5: LVT & carpet tile flooring
C7: PREPARED BY | D7: TAX BASIS | F7: PROPOSAL TOTAL
C8: Dynamic Home Solutions (DHS) | D8: 6.35% on materials | F8: =F43
B10: # | C10: DESCRIPTION | D10: QTY | E10: UNIT PRICE | F10: LINE TOTAL
C11: LABOR
B12: 1 | C12: Install LVT | D12: 2055 | E12: 2.1 | F12: =D12*E12
B13: 2 | C13: Install Carpet Tile | D13: 865 | E13: 0.95 | F13: =D13*E13
B14: 3 | C14: Rip/Haul – Carpet | D14: 822 | E14: 0.45 | F14: =D14*E14
B15: 4 | C15: Rip/haul Existing VCT (1 layer) Sanitation & Hygiene Office | D15: 149 | E15: 1.45 | F15: =D15*E15
B16: 5 | C16: Rip/haul Existing Sheet Vinyl Single Layer Break Room | D16: 164 | E16: 1.45 | F16: =D16*E16
B17: 6 | C17: Rip/haul Existing LVT and VCT Two Layers – All Other Areas | D17: 1639 | E17: 1.45 | F17: =D17*E17
B18: 7 | C18: Rip/haul Existing Luan All Areas with Existing Vinyl Flooring | D18: 1868 | E18: 1.45 | F18: =D18*E18
B19: 8 | C19: Self-Level/Prep | D19: 1868 | E19: 0.7 | F19: =D19*E19
B20: 9 | C20: Install Luan Underlayment – LVT Areas | D20: 2055 | E20: 1.45 | F20: =D20*E20
B21: 10 | C21: Install Luan Underlayment – Carpet Tile Areas | D21: 865 | E21: 1.45 | F21: =D21*E21
B22: 11 | C22: Night and Weekend | D22: 3 | E22: 700 | F22: =D22*E22
B23: 12 | C23: Install Cove Base | D23: 740 | E23: 1.1 | F23: =D23*E23
B24: 13 | C24: Furniture Moving | D24: 14 | E24: 150 | F24: =D24*E24
C26: MATERIALS
B27: 14 | C27: Mannington Spacia LVT Nordic Oak | D27: 2055 | E27: 2.35 | F27: =D27*E27
B28: 15 | C28: Mapei 399 | D28: 6 | E28: 199 | F28: =D28*E28
B29: 16 | C29: Mannington Carpet Tile Style – Silhouette Color-Bonds | D29: 865 | E29: 3.95 | F29: =D29*E29
B30: 17 | C30: Mannington Infinity II Pressure Sensitive Adhesives | D30: 1 | E30: 179.5 | F30: =D30*E30
B31: 18 | C31: Sureply Luan | D31: 92 | E31: 34 | F31: =D31*E31
B32: 19 | C32: Leveler/Prep Materials | D32: 1868 | E32: 0.44 | F32: =D32*E32
B33: 20 | C33: 4" Cove Base 1/8" – customer to select color | D33: 740 | E33: 1.35 | F33: =D33*E33
B34: 21 | C34: Rubber T-caps – customer to select color | D34: 5 | E34: 32 | F34: =D34*E34
C36: FREIGHT & DISTRIBUTION
B37: 22 | C37: Mannington Freight | D37: 1 | E37: 492.5 | F37: =D37*E37
C39: Labor subtotal | F39: =SUM(F12:F18,F20:F24)
C40: Materials subtotal | F40: =SUM(F27:F34)
C41: Freight & distribution | F41: =SUM(F37)
C42: Tax on materials | E42: 0.0635 | F42: =F40*E42
C43: TOTAL | F43: =F39+F40+F41+F42
C44: Deposit due on approval | E44: 0.5 | F44: =F43*E44
C45: Balance due on completion | F45: =F43-F44
B47: PROJECT NOTES, TERMS & CUSTOMER RESPONSIBILITIES
C49: Estimate validity & schedule
B50: • | C50: This estimate is valid for 30 days from the date issued.
B51: • | C51: Product lead time is estimated at 3–6 weeks from approval/order placement (lead times can change).
C53: Payment terms
B54: • | C54: 50% deposit due upfront to release materials and secure scheduling.
B55: • | C55: Remaining balance due upon project completion (final walk-through/substantial completion).
C57: Subfloor & floor prep
B58: • | C58: Floor prep (self-leveling/skim/patch) is included as listed in the line items.
B59: • | C59: Any additional prep required after demo (patching/skim-coating/self-leveling beyond what's included) will be reviewed with the customer and priced as an approved change before proceeding.
B60: • | C60: If moisture issues are discovered, moisture mitigation will be reviewed and priced as an approved change before proceeding.
C62: Work hours & access
B63: • | C63: Estimate accounts for work performed at night and/or over weekends as listed in the scope.
B64: • | C64: Customer to provide site access during scheduled work hours and ensure DHS can work without interruption.
C66: Fixed items
B67: • | C67: DHS will do its best to install neatly around fixed items where removal is not possible.
C69: Customer responsibilities (prior to start of work)
B70: • | C70: Clear access: all areas in scope must be cleared of loose items prior to installation unless included as a line item.
B71: • | C71: Remove/secure electronics, boxes, small items, breakables, and personal belongings from all work areas.
B72: • | C72: Utilities: customer/GC to provide power, lighting, and HVAC as needed for installation.
B73: • | C73: Site logistics: customer/GC to coordinate parking/loading access and access cards/keys.
C75: Dental chairs & equipment
B76: • | C76: Customer is responsible for having dental chair control units and/or equipment attachments disconnected/removed so chairs can be safely moved for installation access.
B77: • | C77: DHS will take reasonable care to protect chairs/equipment but is not responsible for their proper functioning or operation after installation.
B78: • | C78: If chairs/equipment are not properly disconnected at the scheduled start, DHS may pause, reschedule, and/or bill additional labor for delays.
C80: Warranty & cancellations
B81: • | C81: DHS provides a one-year labor warranty on workmanship (see one-pager).
B82: • | C82: Manufacturer warranties apply separately for materials.
B83: • | C83: If the customer cancels or changes product selection after materials are ordered, manufacturer restocking fees and any freight/return costs may apply.
C85: Insurance
B86: • | C86: DHS can provide a Certificate of Insurance upon request.
C88: Exclusions / add-ons
B89: • | C89: Please review the floor plan/scope areas and notify DHS of any discrepancies prior to deposit being initiated.
B90: • | C90: Change orders: any additional work or scope changes must be approved in writing prior to proceeding.

Sheet Chelmsford Office
B3: 42 NORTH | RETAIL FLOORING PROPOSAL | F3: PROPOSAL
B4: Chelmsford Office
B5: Carpet tile flooring
C7: PREPARED BY | D7: TAX BASIS | F7: PROPOSAL TOTAL
C8: Dynamic Home Solutions (DHS) | D8: 6.25% on materials | F8: =F32
B10: # | C10: DESCRIPTION | D10: QTY | E10: UNIT PRICE | F10: LINE TOTAL
C11: LABOR
B12: 1 | C12: Install Carpet Tile | D12: 1055 | E12: 0.95 | F12: =D12*E12
B13: 2 | C13: Rip/Haul – Carpet | D13: 959 | E13: 0.5 | F13: =D13*E13
B14: 3 | C14: Night and Weekend | D14: 2 | E14: 700 | F14: =D14*E14
B15: 4 | C15: Install Cove Base | D15: 275 | E15: 1.1 | F15: =D15*E15
B16: 5 | C16: Furniture Moving | D16: 3 | E16: 150 | F16: =D16*E16
C18: MATERIALS
B19: 6 | C19: Mannington Carpet Tile Style – Silhouette Color-Bonds | D19: 1086.3 | E19: 3.95 | F19: =D19*E19
B20: 7 | C20: Mannington Infinity II Pressure Sensitive Adhesives | D20: 2 | E20: 179.5 | F20: =D20*E20
B21: 8 | C21: Mannington Assure Sealer | D21: 2 | E21: 228.5 | F21: =D21*E21
B22: 9 | C22: 4" Cove Base 1/8" – customer to select color | D22: 275 | E22: 1.35 | F22: =D22*E22
B23: 10 | C23: Rubber T-caps – customer to select color | D23: 7 | E23: 32 | F23: =D23*E23
C25: FREIGHT & DISTRIBUTION
B26: 11 | C26: Freight | D26: 1 | E26: 492.5 | F26: =D26*E26
C28: Labor subtotal | F28: =SUM(F12:F16)
C29: Materials subtotal | F29: =SUM(F19:F23)
C30: Freight & distribution | F30: =SUM(F26)
C31: Tax on materials | E31: 0.0625 | F31: =F29*E31
C32: TOTAL | F32: =F28+F29+F30+F31
C33: Deposit due on approval | E33: 0.5 | F33: =F32*E33
C34: Balance due on completion | F34: =F32-F33
B36: PROJECT NOTES, TERMS & CUSTOMER RESPONSIBILITIES
C38: Estimate validity & schedule
B39: • | C39: This estimate is valid for 30 days from the date issued.
B40: • | C40: Product lead time is estimated at 3–6 weeks from approval/order placement (lead times can change).
C42: Payment terms
B43: • | C43: 50% deposit due upfront to release materials and secure scheduling.
B44: • | C44: Remaining balance due upon project completion (final walk-through/substantial completion).
C46: Subfloor & floor prep
B47: • | C47: Floor prep is not included unless listed as a line item; any prep found to be required after demo will be reviewed with the customer and priced as an approved change before proceeding.
B48: • | C48: If moisture issues are discovered, moisture mitigation will be reviewed and priced as an approved change before proceeding.
C50: Work hours & access
B51: • | C51: Estimate accounts for work performed at night and/or over weekends as listed in the scope.
B52: • | C52: Customer to provide site access during scheduled work hours and ensure DHS can work without interruption.
C54: Fixed items
B55: • | C55: DHS will do its best to install neatly around fixed items where removal is not possible.
C57: Customer responsibilities (prior to start of work)
B58: • | C58: Clear access: all areas in scope must be cleared of loose items prior to installation unless included as a line item.
B59: • | C59: Remove/secure electronics, boxes, small items, breakables, and personal belongings from all work areas.
B60: • | C60: Utilities: customer/GC to provide power, lighting, and HVAC as needed for installation.
B61: • | C61: Site logistics: customer/GC to coordinate parking/loading access and access cards/keys.
C63: Warranty & cancellations
B64: • | C64: DHS provides a one-year labor warranty on workmanship (see one-pager).
B65: • | C65: Manufacturer warranties apply separately for materials.
B66: • | C66: If the customer cancels or changes product selection after materials are ordered, manufacturer restocking fees and any freight/return costs may apply.
C68: Insurance
B69: • | C69: DHS can provide a Certificate of Insurance upon request.
C71: Exclusions / add-ons
B72: • | C72: Please review the floor plan/scope areas and notify DHS of any discrepancies prior to deposit being initiated.
B73: • | C73: Change orders: any additional work or scope changes must be approved in writing prior to proceeding.

Sheet Meriden Dental
B3: 42 NORTH | RETAIL FLOORING PROPOSAL | F3: PROPOSAL
B4: Meriden Dental
B5: LVT & carpet tile flooring — Preferred pricing
C7: PREPARED BY | D7: TAX BASIS | F7: PROPOSAL TOTAL
C8: Dynamic Home Solutions (DHS) | D8: 6.35% on materials | F8: =F40
B10: # | C10: DESCRIPTION | D10: QTY | E10: UNIT PRICE | F10: LINE TOTAL
C11: LABOR
B12: 1 | C12: Install LVT | D12: 1572 | E12: 2.1 | F12: =D12*E12
B13: 2 | C13: Install Carpet Tile | D13: 1176 | E13: 0.95 | F13: =D13*E13
B14: 3 | C14: Rip/Haul – Carpet | D14: 1070 | E14: 0.45 | F14: =D14*E14
B15: 4 | C15: Rip/Haul – Glue Down | D15: 1429 | E15: 1.45 | F15: =D15*E15
B16: 5 | C16: Install Ultraply | D16: 1572 | E16: 1.45 | F16: =D16*E16
B17: 6 | C17: Self-Level/skim | D17: 40 | E17: 43 | F17: =D17*E17
B18: 7 | C18: Night and Weekend | D18: 4 | E18: 700 | F18: =D18*E18
B19: 8 | C19: Install Cove Base | D19: 985 | E19: 1.1 | F19: =D19*E19
B20: 9 | C20: Furniture Moving | D20: 12 | E20: 150 | F20: =D20*E20
C22: MATERIALS
B23: 10 | C23: Mannington Spacia LVT | D23: 1572 | E23: 2.35 | F23: =D23*E23
B24: 11 | C24: MoistureLoc LVT Adhesive | D24: 6 | E24: 199 | F24: =D24*E24
B25: 12 | C25: Mannington Carpet Tile Style – Silhouette Color-Bonds | D25: 1176 | E25: 3.95 | F25: =D25*E25
B26: 13 | C26: Mannington Infinity II Pressure Sensitive Adhesives | D26: 2 | E26: 179.5 | F26: =D26*E26
B27: 14 | C27: Mannington Assure Sealer | D27: 2 | E27: 228.5 | F27: =D27*E27
B28: 15 | C28: Ultraply | D28: 49 | E28: 34 | F28: =D28*E28
B29: 16 | C29: Leveler/Prep Materials | D29: 40 | E29: 34.5 | F29: =D29*E29
B30: 17 | C30: 4" Cove Base 1/8" – customer to select color | D30: 985 | E30: 1.21 | F30: =D30*E30
B31: 18 | C31: Rubber T-caps and stairnose (1) – customer to select color | D31: 12 | E31: 32 | F31: =D31*E31
C33: FREIGHT & DISTRIBUTION
B34: 19 | C34: Mannington Freight | D34: 1 | E34: 492.5 | F34: =D34*E34
C36: Labor subtotal | F36: =SUM(F12:F20)
C37: Materials subtotal | F37: =SUM(F23:F31)
C38: Freight & distribution | F38: =SUM(F34)
C39: Tax on materials | E39: 0.0635 | F39: =F37*E39
C40: TOTAL | F40: =F36+F37+F38+F39
C41: Deposit due on approval | E41: 0.5 | F41: =F40*E41
C42: Balance due on completion | F42: =F40-F41
B44: PROJECT NOTES, TERMS & CUSTOMER RESPONSIBILITIES
C46: Estimate validity & schedule
B47: • | C47: This estimate is valid for 30 days from the date issued.
B48: • | C48: Product lead time is estimated at 3–6 weeks from approval/order placement (lead times can change).
C50: Payment terms
B51: • | C51: 50% deposit due upfront to release materials and secure scheduling.
B52: • | C52: Remaining balance due upon project completion (final walk-through/substantial completion).
C54: Subfloor & floor prep
B55: • | C55: Floor prep (self-leveling/skim/patch) is included as listed in the line items.
B56: • | C56: Any additional prep required after demo (patching/skim-coating/self-leveling beyond what's included) will be reviewed with the customer and priced as an approved change before proceeding.
B57: • | C57: If moisture issues are discovered, moisture mitigation will be reviewed and priced as an approved change before proceeding.
C59: Work hours & access
B60: • | C60: Estimate accounts for work performed at night and/or over weekends as listed in the scope.
B61: • | C61: Customer to provide site access during scheduled work hours and ensure DHS can work without interruption.
C63: Fixed items
B64: • | C64: DHS will do its best to install neatly around fixed items where removal is not possible.
C66: Customer responsibilities (prior to start of work)
B67: • | C67: Clear access: all areas in scope must be cleared of loose items prior to installation unless included as a line item.
B68: • | C68: Remove/secure electronics, boxes, small items, breakables, and personal belongings from all work areas.
B69: • | C69: Utilities: customer/GC to provide power, lighting, and HVAC as needed for installation.
B70: • | C70: Site logistics: customer/GC to coordinate parking/loading access and access cards/keys.
C72: Dental chairs & equipment
B73: • | C73: Customer is responsible for having dental chair control units and/or equipment attachments disconnected/removed so chairs can be safely moved for installation access.
B74: • | C74: DHS will take reasonable care to protect chairs/equipment but is not responsible for their proper functioning or operation after installation.
B75: • | C75: If chairs/equipment are not properly disconnected at the scheduled start, DHS may pause, reschedule, and/or bill additional labor for delays.
C77: Warranty & cancellations
B78: • | C78: DHS provides a one-year labor warranty on workmanship (see one-pager).
B79: • | C79: Manufacturer warranties apply separately for materials.
B80: • | C80: If the customer cancels or changes product selection after materials are ordered, manufacturer restocking fees and any freight/return costs may apply.
C82: Insurance
B83: • | C83: DHS can provide a Certificate of Insurance upon request.
C85: Exclusions / add-ons
B86: • | C86: Please review the floor plan/scope areas and notify DHS of any discrepancies prior to deposit being initiated.
B87: • | C87: Change orders: any additional work or scope changes must be approved in writing prior to proceeding.

Sheet Family Dental Newington
B3: 42 NORTH | RETAIL FLOORING PROPOSAL | F3: PROPOSAL
B4: Family Dental Newington
B5: Carpet tile flooring
C7: PREPARED BY | D7: TAX BASIS | F7: PROPOSAL TOTAL
C8: Dynamic Home Solutions (DHS) | D8: 6.35% on materials | F8: =F34
B10: # | C10: DESCRIPTION | D10: QTY | E10: UNIT PRICE | F10: LINE TOTAL
C11: LABOR
B12: 1 | C12: Install Carpet Tile | D12: 2635 | E12: 0.95 | F12: =D12*E12
B13: 2 | C13: Rip/Haul – Carpet | D13: 2395 | E13: 0.45 | F13: =D13*E13
B14: 3 | C14: Night and Weekend | D14: 1 | E14: 800 | F14: =D14*E14
B15: 4 | C15: Install Cove Base | D15: 900 | E15: 1.1 | F15: =D15*E15
B16: 5 | C16: Furniture Moving | D16: 4 | E16: 150 | F16: =D16*E16
C18: MATERIALS
B19: 6 | C19: Mannington Carpet Tile Silhouette Blocks | D19: 2752 | E19: 3.95 | F19: =D19*E19
B20: 7 | C20: Mannington Infinity II Pressure Sensitive Adhesives | D20: 3 | E20: 179.5 | F20: =D20*E20
B21: 8 | C21: Mannington Assure Sealer | D21: 3 | E21: 228.5 | F21: =D21*E21
B22: 9 | C22: 4" Cove Base 1/8" | D22: 900 | E22: 1.2 | F22: =D22*E22
B23: 10 | C23: Rubber Stairnose for Platforms | D23: 6 | E23: 42 | F23: =D23*E23
B24: 11 | C24: Rubber T-caps | D24: 7 | E24: 32 | F24: =D24*E24
C26: FREIGHT & DISTRIBUTION
B27: 12 | C27: Mannington Freight | D27: 1 | E27: 430 | F27: =D27*E27
B28: 13 | C28: NRF Freight | D28: 1 | E28: 115 | F28: =D28*E28
C30: Labor subtotal | F30: =SUM(F12:F16)
C31: Materials subtotal | F31: =SUM(F19:F24)
C32: Freight & distribution | F32: =SUM(F27:F28)
C33: Tax on materials | E33: 0.0635 | F33: =F31*E33
C34: TOTAL | F34: =F30+F31+F32+F33
C35: Deposit due on approval | E35: 0.5 | F35: =F34*E35
C36: Balance due on completion | F36: =F34-F35
B38: PROJECT NOTES, TERMS & CUSTOMER RESPONSIBILITIES
C40: Estimate validity & schedule
B41: • | C41: This estimate is valid for 30 days from the date issued.
B42: • | C42: Product lead time is estimated at 3–6 weeks from approval/order placement (lead times can change).
C44: Payment terms
B45: • | C45: 50% deposit due upfront to release materials and secure scheduling.
B46: • | C46: Remaining balance due upon project completion (final walk-through/substantial completion).
C48: Subfloor & floor prep
B49: • | C49: Floor prep is not included unless listed as a line item; any prep found to be required after demo will be reviewed with the customer and priced as an approved change before proceeding.
B50: • | C50: If moisture issues are discovered, moisture mitigation will be reviewed and priced as an approved change before proceeding.
C52: Work hours & access
B53: • | C53: Estimate accounts for work performed at night and/or over weekends as listed in the scope.
B54: • | C54: Customer to provide site access during scheduled work hours and ensure DHS can work without interruption.
C56: Fixed items
B57: • | C57: DHS will do its best to install neatly around fixed items where removal is not possible.
C59: Customer responsibilities (prior to start of work)
B60: • | C60: Clear access: all areas in scope must be cleared of loose items prior to installation unless included as a line item.
B61: • | C61: Remove/secure electronics, boxes, small items, breakables, and personal belongings from all work areas.
B62: • | C62: Utilities: customer/GC to provide power, lighting, and HVAC as needed for installation.
B63: • | C63: Site logistics: customer/GC to coordinate parking/loading access and access cards/keys.
C65: Dental chairs & equipment
B66: • | C66: Customer is responsible for having dental chair control units and/or equipment attachments disconnected/removed so chairs can be safely moved for installation access.
B67: • | C67: DHS will take reasonable care to protect chairs/equipment but is not responsible for their proper functioning or operation after installation.
B68: • | C68: If chairs/equipment are not properly disconnected at the scheduled start, DHS may pause, reschedule, and/or bill additional labor for delays.
C70: Warranty & cancellations
B71: • | C71: DHS will provide an extended three-year labor warranty on workmanship performed (see one-pager).
B72: • | C72: Manufacturer warranties apply separately for materials.
B73: • | C73: If the customer cancels or changes product selection after materials are ordered, manufacturer restocking fees and any freight/return costs may apply.
C75: Insurance
B76: • | C76: DHS can provide a Certificate of Insurance upon request.
C78: Exclusions / add-ons
B79: • | C79: Please review the floor plan/scope areas and notify DHS of any discrepancies prior to deposit being initiated.
B80: • | C80: Change orders: any additional work or scope changes must be approved in writing prior to proceeding.

Sheet New Haven Dental Flooring
B3: 42 NORTH | RETAIL FLOORING PROPOSAL | F3: PROPOSAL
B4: New Haven Dental
B5: LVT & carpet tile flooring
C7: PREPARED BY | D7: TAX BASIS | F7: PROPOSAL TOTAL
C8: Dynamic Home Solutions (DHS) | D8: 6.35% on materials | F8: =F38
B10: # | C10: DESCRIPTION | D10: QTY | E10: UNIT PRICE | F10: LINE TOTAL
C11: LABOR
B12: 1 | C12: Install LVT | D12: 1355 | E12: 2.1 | F12: =D12*E12
B13: 2 | C13: Install Carpet Tile | D13: 771 | E13: 0.95 | F13: =D13*E13
B14: 3 | C14: Rip/Haul – Carpet | D14: 688 | E14: 0.45 | F14: =D14*E14
B15: 4 | C15: Rip/Haul – Glue Down | D15: 1209 | E15: 1.45 | F15: =D15*E15
B16: 5 | C16: Self-Level/skim | D16: 1209 | E16: lump sum | F16: 1505
B17: 6 | C17: Night and Weekend | D17: 1 | E17: 700 | F17: =D17*E17
B18: 7 | C18: Install Cove Base | D18: 806 | E18: 1.1 | F18: =D18*E18
B19: 8 | C19: Furniture Moving | D19: 16 | E19: 150 | F19: =D19*E19
C21: MATERIALS
B22: 9 | C22: Mannington Spacia LVT | D22: 1392 | E22: 2.35 | F22: =D22*E22
B23: 10 | C23: Mapei 399 | D23: 4 | E23: 199 | F23: =D23*E23
B24: 11 | C24: Mannington Carpet Tile Style – Silhouette Color-Bonds | D24: 830.7 | E24: 3.95 | F24: =D24*E24
B25: 12 | C25: Mannington Infinity II Pressure Sensitive Adhesives | D25: 2 | E25: 179.5 | F25: =D25*E25
B26: 13 | C26: Self-Leveler Laticrete NXT Level Flow | D26: 35 | E26: 34.5 | F26: =D26*E26
B27: 14 | C27: 4" Cove Base 1/8" – customer to select color | D27: 985 | E27: 1.21 | F27: =D27*E27
B28: 15 | C28: Rubber T-caps and stairnose (1) – customer to select color | D28: 10 | E28: 32 | F28: =D28*E28
C30: FREIGHT & DISTRIBUTION
B31: 16 | C31: Mannington Freight | D31: 1 | E31: 330 | F31: =D31*E31
B32: 17 | C32: NRF Distribution | D32: 1 | E32: 162.5 | F32: =D32*E32
C34: Labor subtotal | F34: =SUM(F12:F19)
C35: Materials subtotal | F35: =SUM(F22:F28)
C36: Freight & distribution | F36: =SUM(F31:F32)
C37: Tax on materials | E37: 0.0635 | F37: =F35*E37
C38: TOTAL | F38: =F34+F35+F36+F37
C39: Deposit due on approval | E39: 0.5 | F39: =F38*E39
C40: Balance due on completion | F40: =F38-F39
B42: PROJECT NOTES, TERMS & CUSTOMER RESPONSIBILITIES
C44: Estimate validity & schedule
B45: • | C45: This estimate is valid for 30 days from the date issued.
B46: • | C46: Product lead time is estimated at 3–6 weeks from approval/order placement (lead times can change).
C48: Payment terms
B49: • | C49: 50% deposit due upfront to release materials and secure scheduling.
B50: • | C50: Remaining balance due upon project completion (final walk-through/substantial completion).
C52: Subfloor & floor prep
B53: • | C53: Floor prep (self-leveling/skim/patch) is included as listed in the line items.
B54: • | C54: Any additional prep required after demo (patching/skim-coating/self-leveling beyond what's included) will be reviewed with the customer and priced as an approved change before proceeding.
B55: • | C55: If moisture issues are discovered, moisture mitigation will be reviewed and priced as an approved change before proceeding.
C57: Work hours & access
B58: • | C58: Estimate accounts for work performed at night and/or over weekends as listed in the scope.
B59: • | C59: Customer to provide site access during scheduled work hours and ensure DHS can work without interruption.
C61: Fixed items
B62: • | C62: DHS will do its best to install neatly around fixed items where removal is not possible.
C64: Customer responsibilities (prior to start of work)
B65: • | C65: Clear access: all areas in scope must be cleared of loose items prior to installation unless included as a line item.
B66: • | C66: Remove/secure electronics, boxes, small items, breakables, and personal belongings from all work areas.
B67: • | C67: Utilities: customer/GC to provide power, lighting, and HVAC as needed for installation.
B68: • | C68: Site logistics: customer/GC to coordinate parking/loading access and access cards/keys.
C70: Dental chairs & equipment
B71: • | C71: Customer is responsible for having dental chair control units and/or equipment attachments disconnected/removed so chairs can be safely moved for installation access.
B72: • | C72: DHS will take reasonable care to protect chairs/equipment but is not responsible for their proper functioning or operation after installation.
B73: • | C73: If chairs/equipment are not properly disconnected at the scheduled start, DHS may pause, reschedule, and/or bill additional labor for delays.
C75: Warranty & cancellations
B76: • | C76: DHS provides a one-year labor warranty on workmanship (see one-pager).
B77: • | C77: Manufacturer warranties apply separately for materials.
B78: • | C78: If the customer cancels or changes product selection after materials are ordered, manufacturer restocking fees and any freight/return costs may apply.
C80: Insurance
B81: • | C81: DHS can provide a Certificate of Insurance upon request.
C83: Exclusions / add-ons
B84: • | C84: Please review the floor plan/scope areas and notify DHS of any discrepancies prior to deposit being initiated.
B85: • | C85: Change orders: any additional work or scope changes must be approved in writing prior to proceeding.
B87: FLOOR PLAN / SCOPE AREAS

Sheet New Haven Dental Painting
B3: 42 NORTH | RETAIL FLOORING PROPOSAL | F3: PROPOSAL
B4: New Haven Dental
B5: Painting & wallpaper removal
C7: PREPARED BY | D7: TAX BASIS | F7: PROPOSAL TOTAL
C8: Dynamic Home Solutions (DHS) | D8: Not applicable | F8: =F16
B10: # | C10: DESCRIPTION | D10: QTY | E10: UNIT PRICE | F10: LINE TOTAL
C11: SCOPE OF WORK
B12: 1 | C12: Painting (includes materials) | D12: 1 | E12: 10500 | F12: =D12*E12
B13: 2 | C13: Wallpaper Removal & Prep | D13: 1 | E13: 6150 | F13: =D13*E13
B14: 3 | C14: Night & Weekend Work | D14: 2 | E14: 700 | F14: =D14*E14
C16: TOTAL | F16: =SUM(F12:F14)
C17: Deposit due on approval | E17: 0.5 | F17: =F16*E17
C18: Balance due on completion | F18: =F16-F17
B20: PROJECT NOTES, TERMS & CUSTOMER RESPONSIBILITIES
C22: Estimate validity & schedule
B23: • | C23: This estimate is valid for 30 days from the date issued.
B24: • | C24: Scheduling will be coordinated upon approval and receipt of deposit.
C26: Payment terms
B27: • | C27: 50% deposit due at signing to secure scheduling.
B28: • | C28: Remaining balance due upon project completion (final walk-through/substantial completion).
C30: Scope & surface prep
B31: • | C31: Painting pricing includes materials as listed.
B32: • | C32: Standard surface prep (minor patching, caulking, sanding, spot-priming) is included.
B33: • | C33: Wallpaper Removal & Prep pricing is an estimate. Additional labor may be required once the wallpaper is removed and the underlying wall condition is assessed; any added scope will be quoted as an approved change before proceeding.
C35: Work hours & access
B36: • | C36: Estimate accounts for work performed at night and/or over weekends as listed in the scope.
B37: • | C37: Customer to provide site access during scheduled work hours and ensure DHS can work without interruption.
C39: Fixed items & protection
B40: • | C40: DHS will mask and protect floors, fixtures, and equipment, and will cut in neatly around fixed items where removal is not possible.
B41: • | C41: DHS will take reasonable care working around dental equipment; DHS is not responsible for the proper functioning or operation of dental equipment after the work.
C43: Customer responsibilities (prior to start of work)
B44: • | C44: Clear access: work areas must be cleared of loose items; customer to remove wall hangings, artwork, electronics, breakables, and personal belongings from all work areas.
B45: • | C45: Utilities: customer/GC to provide power, lighting, and HVAC as needed.
B46: • | C46: Site logistics: customer/GC to coordinate parking/loading access and access cards/keys.
C48: Warranty & cancellations
B49: • | C49: DHS provides a one-year labor warranty on workmanship (see one-pager).
B50: • | C50: Manufacturer warranties apply separately for materials.
C52: Insurance
B53: • | C53: DHS can provide a Certificate of Insurance upon request.
C55: Exclusions / add-ons
B56: • | C56: Change orders: any additional work or scope changes must be approved in writing prior to proceeding.

Sheet Medford - Full (Mat + Labor)
B3: 42 NORTH | RETAIL FLOORING PROPOSAL | F3: PROPOSAL
B4: Medford Office
B5: LVT & carpet tile flooring — Full (Materials + Labor)
C7: PREPARED BY | D7: TAX BASIS | F7: PROPOSAL TOTAL
C8: Dynamic Home Solutions (DHS) | D8: 6.25% on materials | F8: =F35
B10: # | C10: DESCRIPTION | D10: QTY | E10: UNIT PRICE | F10: LINE TOTAL
C11: LABOR
B12: 1 | C12: Install LVT (Glue Down – Concrete) | D12: 89 | E12: 2.9166667 | F12: =D12*E12
B13: 2 | C13: Install Carpet Tile (Glue Down) | D13: 379 | E13: 1.0833333 | F13: =D13*E13
B14: 3 | C14: Install Cove Base | D14: 157 | E14: 1.25 | F14: =D14*E14
B15: 4 | C15: Remove Existing Cove Base | D15: 116 | E15: 0.41666667 | F15: =D15*E15
B16: 5 | C16: Skim Coat/Floor Prep (entire floor) | D16: 468 | E16: 0.83333333 | F16: =D16*E16
B17: 6 | C17: Furniture Moving | D17: 1 | E17: 166.66667 | F17: =D17*E17
C19: MATERIALS
B20: 7 | C20: Altro Lavencia | D20: 108 | E20: 4.5833333 | F20: =D20*E20
B21: 8 | C21: Altro LVT Adhesive (Glue Down) | D21: 1 | E21: 265.21667 | F21: =D21*E21
B22: 9 | C22: Mannington Commercial Carpet Tile 24x24 | D22: 381 | E22: 6.25 | F22: =D22*E22
B23: 10 | C23: Carpet Tile Adhesive | D23: 6 | E23: 203.03333 | F23: =D23*E23
B24: 11 | C24: 4" Cove Base 1/8" (incl. adhesive) | D24: 157 | E24: 1.25 | F24: =D24*E24
B25: 12 | C25: Skim Coat/Leveler | D25: 6 | E25: 35.833333 | F25: =D25*E25
B26: 13 | C26: Rubber T-Mold Transitions | D26: 4 | E26: 36.666667 | F26: =D26*E26
C28: FREIGHT & DISTRIBUTION
B29: 14 | C29: Freight | D29: 1 | E29: 625 | F29: =D29*E29
C31: Labor subtotal | F31: =SUM(F12:F17)
C32: Materials subtotal | F32: =SUM(F20:F26)
C33: Freight & distribution | F33: =SUM(F29)
C34: Tax on materials | E34: 0.0625 | F34: =F32*E34
C35: TOTAL | F35: =F31+F32+F33+F34
C36: Deposit due on approval | E36: 0.5 | F36: =F35*E36
C37: Balance due on completion | F37: =F35-F36
B39: PROJECT NOTES & TERMS
B41: • | C41: 50% deposit due at contract signing; balance due upon completion of work.
B42: • | C42: Pricing valid for 30 days from the proposal date.
B43: • | C43: Quantities are based on field measurements (FloorWizard, 7/10/2026); final billing may adjust to actual installed quantities.
B44: • | C44: Floor prep / skim coat is estimated. If the subfloor requires additional prep once existing flooring is removed, the added prep will be quoted before proceeding.
B45: • | C45: Product colors and selections to be confirmed by customer; pricing may be revised upon final product selection.
C47: DISCLAIMER — CARPET TILE: The new carpet tile will not match the existing carpet tile. Dye lot, color, texture, and style will vary between new and existing material. Customer acknowledges and accepts this visible variation.
B49: FLOOR PLAN / SCOPE AREAS

Sheet Great Hill Dental - Partial
B3: 42 NORTH | RETAIL FLOORING PROPOSAL | F3: PROPOSAL
B4: Great Hill Dental
B5: LVT flooring — Great Hill Dental Partners — Boston, Trenton St
C7: PREPARED BY | D7: TAX BASIS | F7: PROPOSAL TOTAL
C8: Dynamic Home Solutions (DHS) | D8: 6.25% on materials | F8: =F33
B10: # | C10: DESCRIPTION | D10: QTY | E10: UNIT PRICE | F10: LINE TOTAL
C11: LABOR
B12: 1 | C12: Install LVT | D12: 465 | E12: 2.1 | F12: =D12*E12
B13: 2 | C13: Skim Coat | D13: 415 | E13: 1.06 | F13: =D13*E13
B14: 3 | C14: Rip/Haul Existing Vinyl | D14: 415 | E14: 1.45 | F14: =D14*E14
B15: 4 | C15: Install Cove Base | D15: 160 | E15: 1.1 | F15: =D15*E15
B16: 5 | C16: Furniture | D16: 4 | E16: 175 | F16: =D16*E16
B17: 6 | C17: Night and Weekend | D17: 1 | E17: 700 | F17: =D17*E17
C19: MATERIALS
B20: 7 | C20: Mannington Spacia Line - Color TBD | D20: 484 | E20: 2.35 | F20: =D20*E20
B21: 8 | C21: Mapei 399 Pressure Sensitive Adhesive | D21: 1 | E21: 199 | F21: =D21*E21
B22: 9 | C22: Patch | D22: 8 | E22: 34.5 | F22: =D22*E22
B23: 10 | C23: 4" Cove Base 1/8" – customer to select color | D23: 160 | E23: 1.15 | F23: =D23*E23
B24: 11 | C24: Rubber T-caps – customer to select color | D24: 2 | E24: 32 | F24: =D24*E24
C26: FREIGHT & DISTRIBUTION
B27: 12 | C27: Freight | D27: 1 | E27: 450 | F27: =D27*E27
C29: Labor subtotal | F29: =SUM(F12:F17)
C30: Materials subtotal | F30: =SUM(F20:F24)
C31: Freight & distribution | F31: =SUM(F27)
C32: Tax on materials | E32: 0.0625 | F32: =F30*E32
C33: TOTAL | F33: =F29+F30+F31+F32
C34: Deposit due on approval | E34: 0.5 | F34: =F33*E34
C35: Balance due on completion | F35: =F33-F34
B37: PROJECT NOTES, TERMS & CUSTOMER RESPONSIBILITIES
C39: Estimate validity & schedule
B40: • | C40: This estimate is valid for 30 days from the date issued.
B41: • | C41: Product lead time is estimated at 3–6 weeks from approval/order placement (lead times can change).
C43: Payment terms
B44: • | C44: 50% deposit due upfront to release materials and secure scheduling.
B45: • | C45: Remaining balance due upon project completion (final walk-through/substantial completion).
C47: Subfloor & floor prep
B48: • | C48: Floor prep (self-leveling/skim/patch) is included as listed in the line items.
B49: • | C49: Any additional prep required beyond what's included will be reviewed with the customer and priced as an approved change before proceeding.
B50: • | C50: If moisture issues are discovered, moisture mitigation will be reviewed and priced as an approved change before proceeding.
B51: • | C51: Scope includes rip-out and haul-away of the existing vinyl flooring in the areas listed.
C53: Work hours & access
B54: • | C54: Estimate accounts for work performed at night and/or over weekends as listed in the scope.
B55: • | C55: Night and/or weekend labor is priced for one (1) shift; additional shifts would be reviewed and priced as an approved change.
B56: • | C56: Customer to provide site access during scheduled work hours and ensure DHS can work without interruption.
C58: Fixed items
B59: • | C59: DHS will do its best to install neatly around fixed items where removal is not possible.
C61: Customer responsibilities (prior to start of work)
B62: • | C62: Clear access: all areas in scope must be cleared of loose items prior to installation unless included as a line item.
B63: • | C63: Remove/secure electronics, boxes, small items, breakables, and personal belongings from all work areas.
B64: • | C64: Utilities: customer/GC to provide power, lighting, and HVAC as needed for installation.
B65: • | C65: Site logistics: customer/GC to coordinate parking/loading access and access cards/keys.
B66: • | C66: Mannington Spacia LVT color is TBD — customer to select prior to ordering. Lead time and freight are subject to the color/product selected.
B67: • | C67: 4" cove base and rubber T-cap colors to be selected by the customer prior to installation.
C69: Dental chairs & equipment
B70: • | C70: Customer is responsible for having dental chair control units and/or equipment attachments disconnected/removed so chairs can be safely moved for installation access.
B71: • | C71: DHS will take reasonable care to protect chairs/equipment but is not responsible for their proper functioning or operation after installation.
B72: • | C72: If chairs/equipment are not properly disconnected at the scheduled start, DHS may pause, reschedule, and/or bill additional labor for delays.
C74: Warranty & cancellations
B75: • | C75: DHS provides a one-year labor warranty on workmanship (see one-pager).
B76: • | C76: Manufacturer warranties apply separately for materials.
B77: • | C77: If the customer cancels or changes product selection after materials are ordered, manufacturer restocking fees and any freight/return costs may apply.
C79: Insurance
B80: • | C80: DHS can provide a Certificate of Insurance upon request.
C82: Exclusions / add-ons
B83: • | C83: Please review the floor plan/scope areas and notify DHS of any discrepancies prior to deposit being initiated.
B84: • | C84: Change orders: any additional work or scope changes must be approved in writing prior to proceeding.
B86: FLOOR PLAN / SCOPE AREAS

Sheet Great Hill Dental Full LVP
B3: 42 NORTH | RETAIL FLOORING PROPOSAL | F3: PROPOSAL
B4: Great Hill Dental
B5: LVT flooring — Great Hill Dental Partners — Boston, Tremont St
C7: PREPARED BY | D7: TAX BASIS | F7: PROPOSAL TOTAL
C8: Dynamic Home Solutions (DHS) | D8: 6.25% on materials | F8: =F34
B10: # | C10: DESCRIPTION | D10: QTY | E10: UNIT PRICE | F10: LINE TOTAL
C11: LABOR
B12: 1 | C12: Install LVT | D12: 2818 | E12: 2.1 | F12: =D12*E12
B13: 2 | C13: Rip/Haul Existing Glue-Down Flooring | D13: 2561 | E13: 1.45 | F13: =D13*E13
B14: 3 | C14: Self-Level/Skim Coat | D14: 30 | E14: 43 | F14: =D14*E14
B15: 4 | C15: Night and Weekend | D15: 2 | E15: 700 | F15: =D15*E15
B16: 5 | C16: Install Cove Base | D16: 960 | E16: 1.1 | F16: =D16*E16
B17: 6 | C17: Furniture Moving | D17: 23 | E17: 150 | F17: =D17*E17
C19: MATERIALS
B20: 7 | C20: Mannington Spacia LVT - Color TBD | D20: 2827.5 | E20: 2.35 | F20: =D20*E20
B21: 8 | C21: Mapei 399 | D21: 5 | E21: 199 | F21: =D21*E21
B22: 9 | C22: Proma Patch | D22: 30 | E22: 32 | F22: =D22*E22
B23: 10 | C23: 4" Cove Base 1/8" – customer to select color | D23: 960 | E23: 1.15 | F23: =D23*E23
B24: 11 | C24: Rubber T-caps – customer to select color | D24: 7 | E24: 32 | F24: =D24*E24
C26: FREIGHT & DISTRIBUTION
B27: 12 | C27: Freight – Mannington | D27: 1 | E27: 510 | F27: =D27*E27
B28: 13 | C28: Freight – NRF | D28: 1 | E28: 115 | F28: =D28*E28
C30: Labor subtotal | F30: =SUM(F12:F17)
C31: Materials subtotal | F31: =SUM(F20:F24)
C32: Freight & distribution | F32: =SUM(F27:F28)
C33: Tax on materials | E33: 0.0625 | F33: =F31*E33
C34: TOTAL | F34: =F30+F31+F32+F33
C35: Deposit due on approval | E35: 0.5 | F35: =F34*E35
C36: Balance due on completion | F36: =F34-F35
B38: PROJECT NOTES, TERMS & CUSTOMER RESPONSIBILITIES
C40: Estimate validity & schedule
B41: • | C41: This estimate is valid for 30 days from the date issued.
B42: • | C42: Product lead time is estimated at 3–6 weeks from approval/order placement (lead times can change).
C44: Payment terms
B45: • | C45: 50% deposit due upfront to release materials and secure scheduling.
B46: • | C46: Remaining balance due upon project completion (final walk-through/substantial completion).
C48: Subfloor & floor prep
B49: • | C49: Floor prep (self-leveling/skim coat and patch) is included as listed, priced at 30 bags; this is an estimate — additional prep will be quoted and approved before proceeding.
B50: • | C50: Any additional prep required beyond what's included will be reviewed with the customer and priced as an approved change before proceeding.
B51: • | C51: If moisture issues are discovered, moisture mitigation will be reviewed and priced as an approved change before proceeding.
B52: • | C52: Scope includes rip-out and haul-away of the existing glue-down flooring (approx. 2,561 SF).
C54: Work hours & access
B55: • | C55: Estimate accounts for work performed at night and/or over weekends as listed in the scope.
B56: • | C56: Night and/or weekend labor is priced for two (2) shifts; additional shifts would be reviewed and priced as an approved change.
B57: • | C57: Customer to provide site access during scheduled work hours and ensure DHS can work without interruption.
C59: Fixed items
B60: • | C60: DHS will do its best to install neatly around fixed items where removal is not possible.
C62: Customer responsibilities (prior to start of work)
B63: • | C63: Clear access: all areas in scope must be cleared of loose items prior to installation unless included as a line item.
B64: • | C64: Remove/secure electronics, boxes, small items, breakables, and personal belongings from all work areas.
B65: • | C65: Utilities: customer/GC to provide power, lighting, and HVAC as needed for installation.
B66: • | C66: Site logistics: customer/GC to coordinate parking/loading access and access cards/keys.
B67: • | C67: Mannington Spacia LVT color is TBD — customer to select prior to ordering. Lead time and freight are subject to the color/product selected.
B68: • | C68: LVP material quantity (2,827.5 SF) is carton-rounded above the 2,818 SF install area (approx. 0.3% overage).
B69: • | C69: 4" cove base and rubber T-cap colors to be selected by the customer prior to installation.
C71: Dental chairs & equipment
B72: • | C72: Customer is responsible for having dental chair control units and/or equipment attachments disconnected/removed so chairs can be safely moved for installation access.
B73: • | C73: DHS will take reasonable care to protect chairs/equipment but is not responsible for their proper functioning or operation after installation.
B74: • | C74: If chairs/equipment are not properly disconnected at the scheduled start, DHS may pause, reschedule, and/or bill additional labor for delays.
C76: Warranty & cancellations
B77: • | C77: DHS provides a one-year labor warranty on workmanship (see one-pager).
B78: • | C78: Manufacturer warranties apply separately for materials.
B79: • | C79: If the customer cancels or changes product selection after materials are ordered, manufacturer restocking fees and any freight/return costs may apply.
C81: Insurance
B82: • | C82: DHS can provide a Certificate of Insurance upon request.
C84: Exclusions / add-ons
B85: • | C85: Freight is a flat rate of $625.00 total and is not taxed.
B86: • | C86: Please review the floor plan/scope areas and notify DHS of any discrepancies prior to deposit being initiated.
B87: • | C87: Change orders: any additional work or scope changes must be approved in writing prior to proceeding.
B89: FLOOR PLAN / SCOPE AREAS

Sheet Selinsgrove
B3: 42 NORTH | RETAIL FLOORING PROPOSAL | F3: PROPOSAL
B4: Dental Care Associates Selinsgrove
B5: LVT & carpet tile flooring — 2 Atrium Court, Selinsgrove, PA 17870
C7: PREPARED BY | D7: TAX BASIS | F7: PROPOSAL TOTAL
C8: Dynamic Home Solutions (DHS) | D8: Included in price (PA) | F8: =F38
B10: # | C10: DESCRIPTION | D10: QTY | E10: UNIT PRICE | F10: LINE TOTAL
C11: LABOR
B12: 1 | C12: Install LVT | D12: 4573 | E12: 2.31 | F12: =D12*E12
B13: 2 | C13: Install Carpet Tile | D13: 1890 | E13: 1.045 | F13: =D13*E13
B14: 3 | C14: Rip/Haul – Glue Down Vinyl | D14: 4157 | E14: 1.595 | F14: =D14*E14
B15: 4 | C15: Rip/Haul – Carpet | D15: 1718 | E15: 0.495 | F15: =D15*E15
B16: 5 | C16: Skim Coat (all LVT areas) | D16: 84 | E16: 47.3 | F16: =D16*E16
B17: 6 | C17: Install Cove Base | D17: 2300 | E17: 1.21 | F17: =D17*E17
B18: 7 | C18: Furniture Moving | D18: 20 | E18: 165 | F18: =D18*E18
B19: 8 | C19: 30 Yard Dumpster (pass through) | D19: 1 | E19: 1000 | F19: =D19*E19
C21: MATERIALS
B22: 9 | C22: Mannington Spacia LVT | D22: 4573 | E22: 2.49 | F22: =D22*E22
B23: 10 | C23: Mapei 399 Pressure Sensitive Adhesive | D23: 13 | E23: 137.8 | F23: =D23*E23
B24: 11 | C24: Mannington Carpet Tile | D24: 1890 | E24: 4.19 | F24: =D24*E24
B25: 12 | C25: Mannington Infinity II Pressure Sensitive Adhesive | D25: 3 | E25: 190.27 | F25: =D25*E25
B26: 13 | C26: Mannington Assure Sealer | D26: 3 | E26: 242.21 | F26: =D26*E26
B27: 14 | C27: Skim Coat / Leveler (Mapei Novaplan HFL / Ardex) | D27: 84 | E27: 36.57 | F27: =D27*E27
B28: 15 | C28: 4" Cove Base 1/8" – customer to select color | D28: 2300 | E28: 1.28 | F28: =D28*E28
B29: 16 | C29: Rubber T-Mold – customer to select color | D29: 10 | E29: 33.92 | F29: =D29*E29
C31: FREIGHT & DISTRIBUTION
B32: 17 | C32: Freight | D32: 1 | E32: 492.5 | F32: =D32*E32
C34: Labor subtotal | F34: =SUM(F12:F19)
C35: Materials subtotal | F35: =SUM(F22:F29)
C36: Freight & distribution | F36: =SUM(F32)
C37: Pennsylvania sales & use tax | F37: Included
C38: TOTAL | F38: =F34+F35+F36
C39: Deposit due on approval | E39: 0.5 | F39: =F38*E39
C40: Balance due on completion | F40: =F38-F39
B42: PROJECT NOTES, TERMS & CUSTOMER RESPONSIBILITIES
C44: Basis of estimate — prepared from plans (no site visit)
B45: • | C45: This proposal has been prepared from the architectural plans and takeoff shown. DHS has not visited this location in person and has not performed a field measure or physical inspection of existing conditions.
B46: • | C46: Quantities, subfloor construction, existing floor coverings, access and site logistics are based on the plans provided and remain subject to verification.
B47: • | C47: DHS recommends a pre-installation site visit before this proposal is finalized, and will gladly schedule one at 42 North's request and convenience.
B48: • | C48: Should conditions on site differ from the plans, affected quantities and pricing will be reviewed with the customer and adjusted by approved change order before work proceeds.
C50: Floor plan & scope confirmation
B51: • | C51: The attached floor plan reflects the takeoff for this proposal. All areas shown in PINK are glue-down LVT. All areas shown in YELLOW are carpet tile.
B52: • | C52: Please review the plan and confirm all areas, and notify DHS of any discrepancies prior to deposit being initiated. Quantities are firm to the plan as shown.
C54: Taxes
B55: • | C55: This is a construction contract for the installation of floor covering. Under Pennsylvania law the contract price is inclusive of all applicable PA sales and use taxes; no separate sales tax is billed.
C57: Estimate validity & schedule
B58: • | C58: This estimate is valid for 30 days from the date issued.
B59: • | C59: Product lead time is estimated at 3–6 weeks from approval/order placement (lead times can change).
B60: • | C60: Estimated on-site duration is 6–10 working days, assuming areas are ready and materials are on site.
C62: Payment terms
B63: • | C63: 50% deposit due upfront to release materials and secure scheduling.
B64: • | C64: Remaining balance due upon project completion (final walk-through/substantial completion).
C66: Subfloor & floor prep
B67: • | C67: A skim coat of all LVT areas is included as listed in the line items.
B68: • | C68: Any additional prep required after demo (patching / self-leveling beyond what is included) will be reviewed with the customer and priced as an approved change before proceeding.
B69: • | C69: Scope includes rip-out and haul-away of the existing glue-down vinyl and carpet in the areas listed.
C71: Moisture mitigation — concrete subfloor (important)
B72: • | C72: The substrate is a concrete slab currently covered by existing glue-down flooring. Slab condition and moisture content cannot be determined until the existing flooring is removed.
B73: • | C73: Accordingly, no moisture testing or moisture mitigation is included in this proposal.
B74: • | C74: Following demolition, DHS will test the slab per ASTM F2170 (in-situ RH) and/or ASTM F1869 (calcium chloride) and share results with the customer.
B75: • | C75: If readings exceed the manufacturer's published limits, mitigation is required and will be quoted and approved as a change order before work proceeds, at a minimum of $2.75 per square foot of affected area.
B76: • | C76: Where a large number of areas require remediation, a grinding machine rental may be necessary at $3,000 per day.
B77: • | C77: Installing over a slab that exceeds the manufacturer's moisture limits will void the material warranty.
B78: • | C78: If mitigation is required, the project schedule will extend to allow for application and cure time.
C80: Work hours & access
B81: • | C81: No night or weekend work is included in this proposal. If weekend work is required for common areas, it will be charged at a rate of $770 per weekend.
B82: • | C82: Customer to provide site access during scheduled work hours and ensure DHS can work without interruption.
C84: Fixed items
B85: • | C85: DHS will do its best to install neatly around fixed items where removal is not possible.
C87: Customer responsibilities (prior to start of work)
B88: • | C88: Clear access: all areas in scope must be cleared of loose items prior to installation unless included as a line item.
B89: • | C89: Remove/secure electronics, boxes, small items, breakables, and personal belongings from all work areas.
B90: • | C90: Utilities: customer/GC to provide power, lighting, and HVAC as needed for installation.
B91: • | C91: Carpet tile, LVT, cove base and T-mold colors to be selected by the customer prior to ordering.
C93: Dental chairs & equipment
B94: • | C94: Customer is responsible for having dental chair control units and/or equipment attachments disconnected/removed so chairs can be safely moved for installation access.
B95: • | C95: DHS will take reasonable care to protect chairs/equipment but is not responsible for their proper functioning or operation after installation.
B96: • | C96: If chairs/equipment are not properly disconnected at the scheduled start, DHS may pause, reschedule, and/or bill additional labor for delays.
C98: Warranty & cancellations
B99: • | C99: DHS will provide an extended three-year labor warranty on workmanship performed (see one-pager).
B100: • | C100: Manufacturer warranties apply separately for materials.
B101: • | C101: If the customer cancels or changes product selection after materials are ordered, manufacturer restocking fees and any freight/return costs may apply.
C103: Insurance
B104: • | C104: DHS can provide a Certificate of Insurance upon request.
C106: Exclusions / add-ons
B107: • | C107: Excludes painting/wallpaper, plumbing or fixture resets, unforeseen subfloor repair and prevailing-wage requirements.
B108: • | C108: Change orders: any additional work or scope changes must be approved in writing prior to proceeding.
B110: FLOOR PLAN / SCOPE AREAS

Sheet Claude Log
A1: Turn # | B1: Date | C1: User Request | D1: Action Taken | E1: Details | F1: Outcome
A2: 4 | B2: 46225 | C2: Excel agent (Master Quoting Database) requested a new customer-facing 'New Haven Dental' proposal tab from shared JSON, matching Family Dental Newington styling, no cost/margin columns. | D2: Created 'New Haven Dental' tab: 17 line items (8 Labor, 7 Material, 2 Freight), Description/Units/Unit Price/Line Total, plus Labor/Materials/Freight subtotals, 6.25% tax, Total, Deposit(50%). Styled to match Family Dental Newington. | E2: Line totals =Bn*Cn (D5:D21); Labor =SUM(D5:D12); Materials =SUM(D13:D19); Freight =SUM(D20:D21); Tax =D23*0.0625; Total =D22+D23+D24+D25; Deposit =D26/2. Accounting format, Aptos Narrow, brand colors #156082/#44B3E1/#C0E6F5. Recreated Claude Log (had been deleted). | F2: Verified: Total $22,488.19, Deposit $11,244.10 match JSON spec. No errors. Reported back to Excel agent.
A3: 5 | B3: 46225 | C3: User corrected the New Haven Dental tax rate to 6.35% (shared spec had 6.25%). | D3: Updated A25 label to 'Tax on Materials (6.35%)' and D25 formula to =D23*0.0635 on New Haven Dental. | E3: Tax now $662.10; downstream Total (=D22+D23+D24+D25) and Deposit (=D26/2) recalculated automatically. | F3: Verified: Tax $662.10, Total $22,498.62, Deposit $11,249.31. Flagged the spec discrepancy to the Excel agent.
A4: 6 | B4: 46225 | C4: User uploaded the DHS 'Gentle Dental Peabody' estimate PDF and asked to scrape the contract notes into the appropriate tab(s). | D4: Extracted the 'Project Notes, Terms & Customer Responsibilities' section and appended it to the Completed-GD Peabody tab (rows 31-68) as a formatted notes block. | E4: 10 subsections (schedule, payment, subfloor/prep, work hours, fixed items, customer responsibilities, dental chairs, warranty, insurance, exclusions). Navy header bar + italic source line + bold subheads + wrapped bullets, merged A:D, sized row heights. Source: DHS Estimate 4326-1, dated 4/3/2026. | F4: Added to Peabody tab only (contract is Peabody-specific). Verified via read-back and rendered image; wrapping and styling confirmed clean.
A5: 7 | B5: 46225 | C5: User asked to add the contract notes to all customer-facing tabs, tailored to each job's scope (add what's needed, remove what's not). | D5: Appended a tailored 'Project Notes, Terms & Customer Responsibilities' block below the proposal on all 14 remaining customer-facing tabs (Peabody already had it). | E5: Tailoring: dental-chairs section only on 11 dental tabs (dropped for Quincy, Chelmsford, Vermont); night/weekend bullet only where that line item exists (dropped for Natick, Vermont); prep 'included as listed' vs 'not included unless listed' per line items; Abington got grind/moisture-mitigation-included wording; Peabody-only specifics (room grinding, $2.75/sf, 4-8 day duration, estimate #) left off other tabs. Same styling as Peabody block. | F5: All 14 blocks verified programmatically (header, sections, last bullet, no bold anomalies) + visual spot-check on Family Dental Newington. No conflicts; all blocks written below existing content.
A6: 8 | B6: 46225 | C6: User uploaded the Newington estimate PDF and asked to check it for 3-year warranty verbiage. | D6: Confirmed the estimate grants an extended three-year labor warranty; updated the warranty bullet on Family Dental Newington (A50) from the generic one-year wording to the estimate's three-year verbiage, with a source note. | E6: Other minor differences noted between the estimate PDF and the generic notes block on that tab: PDF adds an on-site duration bullet (2-4 working days / 1-2 weekends), has a lighter subfloor-prep section (no moisture bullet), and no floor-plan review bullet. Not changed - flagged to user. | F6: A50 verified by read-back. Other tabs still carry the standard one-year warranty wording pending their estimate PDFs.
A7: 9 | B7: 46225 | C7: Excel agent (master quoting database) requested a customer-facing retail proposal tab 'New Haven Dental Painting' from a shared JSON spec, with the wallpaper pricing caveat as a visible callout. | D7: Created 'New Haven Dental Painting' tab (positioned after New Haven Dental Flooring): 3 line items, Total =SUM(D5:D7), Deposit =D8/2; added visible PROJECT NOTES block (rows 11-13) with the wallpaper caveat + deposit terms, plus a cell comment on A6. | E7: No tax row (per spec summary). Styling matched other proposal tabs: navy title/subtitle bar, sky header, accounting number format, Aptos Narrow, column widths copied from New Haven Dental Flooring. First write attempt failed (workbook lost focus - InactiveWorkbook); retried idempotently and succeeded. | F7: Verified by read-back: Total $18,050, Deposit $9,025, all formulas live, notes merged/wrapped. Confirmed back to the Excel agent.
A8: 10 | B8: 46225 | C8: User asked whether other notes should be added for the painting scope. | D8: Expanded the New Haven Dental Painting notes into the full standard terms block (rows 11-38), tailored to painting: validity/scheduling, payment, scope & surface prep (incl. wallpaper caveat), night/weekend work hours, fixed items & protection (masking + dental equipment care), customer responsibilities (wall hangings/electronics), 1-yr warranty, insurance, change orders. | E8: Dropped flooring-specific items (subfloor/moisture, product lead time, dental chair disconnection for floor access); folded the original wallpaper + deposit bullets into their sections. Cell comment on A6 wallpaper line retained. | F8: Verified: 28 lines, no blanks, header/last bullet correct, visual render clean. Same styling as other tabs' notes blocks.
A9: 11 | B9: 46225 | C9: Excel agent (master quoting database) requested two customer-facing Medford proposal tabs from shared JSON specs, with all notes visible and the carpet-tile disclaimer rendered prominently. | D9: Created 'Medford- Full (Mat + Labor)' (14 items, summary rows 19-24, notes 26-32) and 'Medford- Labor + Install Mat' (10 items, summary rows 15-19, notes 21-28), both positioned after New Haven Dental Painting. | E9: Live formulas throughout (D=B*C, subtotals, tax =Materials*0.0625, Total, Deposit /2). Full tab: Total $7,321.35 / Deposit $3,660.67. Labor tab: Total $2,622.89 / Deposit $1,311.45 - both match specs. Disclaimer as bold dark-red on light-yellow merged row + cell comments on the carpet-tile lines (A13 full tab / A6 labor tab). First write hit InactiveWorkbook; retried idempotently. | F9: Verified by read-back + visual render: totals tie to spec, no formula errors, disclaimer prominent. Confirmed back to the Excel agent.
A10: 12 | B10: 46225 | C10: User asked how to share the workbook with a customer as a locked (view-only) external sheet that stays live as new quotes are added. | D10: Advised (no workbook changes): Save a Copy to OneDrive/SharePoint containing only that customer's tabs, then Share > link set to 'Can view' (optionally Block download). AutoSave keeps it live for the customer. | E10: Warned that sharing this workbook directly would expose all customers' tabs + Claude Log; view-only link is the real lock, sheet passwords optional (noted prior lockout risk). Offered to protect sheets in the copy if opened with the add-in. | F10: Guidance only; awaiting user action. No cells modified.
A11: 13 | B11: 46225 | C11: User wants to share this entire file live with the customer, minus the Claude Log. | D11: Set Claude Log sheet visibility to VeryHidden (not unhidable from Excel UI, even in a downloaded copy). Gave share steps: Share > Can view link + Block download; AutoSave keeps it live. | E11: VeryHidden chosen over regular Hidden so right-click Unhide can't reveal it; log remains writable by the add-in and I can unhide on request. Sheet1 no longer exists (user deleted it); all other 18 tabs are visible proposals. | F11: Verified visibility = VeryHidden via read-back. Workbook ready to share as-is.
A12: 14 | B12: 46233 | C12: Excel agent (master quoting database) requested a new customer-facing 'Great Hill Dental - Customer' tab from a shared JSON spec, styled to match the Portland Dental customer tab exactly. | D12: Duplicated 'Completed-Portland Dental' to the end of the workbook, renamed it 'Great Hill Dental - Customer', inserted one extra line-item row (12 items vs 11), and wrote the Great Hill values/formulas into rows 1-22. | E12: Line totals =Bn*Cn (D5:D16); Labor =SUM(D5:D10); Materials =SUM(D11:D15); Freight =SUM(D16); Tax =D18*0.0625; Total =D17+D18+D19+D20; Deposit =D21/2. Column widths A320/B60/C90/D100. Duplicating the Portland tab (rather than rebuilding) preserved fonts, brand fills, accounting formats and the full PROJECT NOTES block, which now sits at rows 24-57. | F12: Verified by read-back: Labor $3,594.15, Materials $1,860.40, Freight $450.00, Tax $116.28, Total $6,020.83, Deposit $3,010.41 - all tie to the spec. No formula errors.
A13: 15 | B13: 46233 | C13: Excel agent asked to keep the generic dental terms and add four Great Hill-specific note lines: LVT color TBD (lead time/freight subject to selection), cove base + T-cap color selection, rip-out/haul-away included, and night/weekend labor priced for one shift. | D13: Inserted 4 rows into the notes block on 'Great Hill Dental - Customer' and wrote the new bullets: A35 (rip-out/haul-away, end of Subfloor & floor prep), A38 (one-shift night/weekend, under Work hours & access), A47-A48 (LVT color TBD and cove base/T-cap color selection, end of Customer responsibilities). | E13: Rows inserted bottom-up (45:46, then 37, then 35) so indices didn't shift mid-edit. New rows inherited the bullet styling from the row above (10pt Aptos Narrow, black, wrapped, merged A:D, 15pt height) - matches the rest of the block. Nothing removed per instruction; notes block now runs rows 24-61. | F13: Verified by read-back and a rendered image of rows 31-52: bullets sit in the right sections, no bold/style anomalies, no clipping. Pricing rows 1-22 untouched.
... A21: 23 | B21: 46289 | C21: User asked to re-engineer the whole workbook so it is far more presentable: modern, better than McKinsey / Goldman Sachs formatting, Garamond or Times New Roman font. | D21: Rebuilt every proposal tab on one design system (Garamond, brand navy #156082 / sky #44B3E1, hairline rules, grouped LABOR / MATERIALS / FREIGHT sections, summary block with TOTAL, 50% deposit and balance, restyled notes, floor plans retained) and added an Overview tab with live cross-sheet totals, KPI tiles and hyperlinks. | E21: All quantities, unit prices and line totals carried over unchanged; every total is a live formula (line = qty x price, subtotals = SUM of section, tax = materials x rate cell, deposit = total x 50%). Tab names normalised (e.g. "Completed - GD Braintree"); Claude Log kept veryHidden. Original numeric anomalies preserved and flagged to the user: Sunrise labor subtotal omits the Self-Level/Prep line; Natick $225 and New Haven $1,505 lump-sum lines shown as "lump sum" with their original quantities; Trenton vs Tremont St on the two Great Hill tabs. | F21: Every line total, subtotal, tax, total and deposit verified equal to the original workbook to the cent on all 20 tabs; recalculation returned zero formula errors.
